{
  "stage": "accumulation_tracking",
  "jobId": "0604a397-e444-4b09-a619-3d20690c0c89",
  "apiCall": 6,
  "timestamp": "2025-07-21T08:10:22.034Z",
  "accumulation": {
    "previousCreatorsCount": 51,
    "newCreatorsCount": 5,
    "totalAccumulatedCount": 54,
    "duplicatesRemoved": 2
  },
  "usernames": [
    "livingthehype_",
    "crepdogcrew",
    "hide.and.sneak",
    "klekt",
    "platinumshoecare",
    "thatsodsoho",
    "minicostore.in",
    "imanshop_tr",
    "c.kickss",
    "doubleboxed",
    "arlegend2",
    "nenoo_store.official",
    "nike",
    "instakicksz",
    "sneakerfreakermag",
    "lindamont",
    "bennetts_",
    "ikaatoni",
    "dropinfos",
    "suhanasethiofficial",
    "bosscosgoodiez",
    "sneakr_tweakr",
    "kronickstyle",
    "mercurialkicks",
    "cxstiillo",
    "itsyourdb",
    "chenxiami99",
    "stockxkicks_net",
    "ridhi.culous",
    "sneakherscanada",
    "madisonpaynestyle",
    "onechance4u",
    "qiasomar",
    "luxury_fty",
    "commonhype",
    "centren",
    "sneakay38",
    "mioteens.sr",
    "id4shoes",
    "zahwaqilah",
    "untiedau",
    "freudonidas",
    "nbcnewyork",
    "freshwitblossom",
    "kckd_rosko",
    "iamharshkale",
    "noahxblack",
    "svweeart",
    "gj5_suratcity",
    "bbcx0102",
    "grwvineeth",
    "shoes.lks",
    "wethenew",
    "stylerunner"
  ]
}