{
  "stage": "accumulation_tracking",
  "jobId": "50307430-9c22-48e1-a526-9cf13c8eede0",
  "apiCall": 2,
  "timestamp": "2025-07-21T10:20:18.513Z",
  "accumulation": {
    "previousCreatorsCount": 9,
    "newCreatorsCount": 11,
    "totalAccumulatedCount": 11,
    "duplicatesRemoved": 9
  },
  "usernames": [
    "imaaduuddin",
    "phonesvendor",
    "irina.tech",
    "applefix.cl",
    "earpods_kenya",
    "technoshop.kaz",
    "ecasetech",
    "kuxiutech",
    "sahabat.gajet11",
    "custom_adventurist",
    "smart_watch_dz16"
  ]
}