{
  "timestamp": "2025-07-21T10:30:23.063Z",
  "platform": "instagram",
  "searchType": "keyword",
  "request": {
    "keywords": [
      "airpods pro"
    ],
    "targetResults": 100,
    "platform": "Instagram"
  },
  "response": {
    "items": [
      {
        "creator": {
          "name": "Karl Conrad",
          "uniqueId": "karlconrad",
          "followers": 135614,
          "avatarUrl": "https://scontent-lga3-1.cdninstagram.com/v/t51.2885-19/57761958_1187980198040019_4819163609185648640_n.jpg?stp=dst-jpg_e0_s150x150_tt6&_nc_ht=scontent-lga3-1.cdninstagram.com&_nc_cat=103&_nc_oc=Q6cZ2QG5_V1AFFHCiZSUWU0qq3jNsVTGP0DQJkT8rVfDrmdo3slyiLIcBRmpuO-HDWyhuqA&_nc_ohc=1a60EpY8d2cQ7kNvwFl2mfJ&_nc_gid=vfruqG5mttwzjkDLoQkY0A&edm=AL2I2h8BAAAA&ccb=7-5&ig_cache_key=GKZgcQPTUbQxdjgEAAAAAADFG_FCbkULAAAB-ccb7-5&oh=00_AfRzEgVs2y4T561VeFQJw2OHKIRLuJSGy11rXMDToHWv-A&oe=6883F22B&_nc_sid=026283",
          "profilePicUrl": "https://scontent-lga3-1.cdninstagram.com/v/t51.2885-19/57761958_1187980198040019_4819163609185648640_n.jpg?stp=dst-jpg_e0_s150x150_tt6&_nc_ht=scontent-lga3-1.cdninstagram.com&_nc_cat=103&_nc_oc=Q6cZ2QG5_V1AFFHCiZSUWU0qq3jNsVTGP0DQJkT8rVfDrmdo3slyiLIcBRmpuO-HDWyhuqA&_nc_ohc=1a60EpY8d2cQ7kNvwFl2mfJ&_nc_gid=vfruqG5mttwzjkDLoQkY0A&edm=AL2I2h8BAAAA&ccb=7-5&ig_cache_key=GKZgcQPTUbQxdjgEAAAAAADFG_FCbkULAAAB-ccb7-5&oh=00_AfRzEgVs2y4T561VeFQJw2OHKIRLuJSGy11rXMDToHWv-A&oe=6883F22B&_nc_sid=026283",
          "verified": true,
          "bio": "Follow for more content + across all platforms!",
          "emails": [],
          "qualityScore": 1075,
          "engagementRate": 0
        },
        "video": {
          "description": "NEW AirPods 4 with Active Noise Cancelling 👌🏻\n\n$179 🇺🇸/ $249 🇨🇦 - Def a cheaper option than AirPods Pro and I've always been a fan of non silicone tip Earbuds! \n\n#airpods #airpods4 #headphones #earbuds #tech #technology #apple #viraltech #unboxing #techunboxing #reels",
          "url": "https://www.instagram.com/reel/DAJOI3WuxMH",
          "statistics": {
            "likes": 2433,
            "comments": 19,
            "views": 98203,
            "shares": 0
          }
        },
        "hashtags": [
          "#airpods",
          "#airpods4",
          "#headphones",
          "#earbuds",
          "#tech",
          "#technology",
          "#apple",
          "#viraltech",
          "#unboxing",
          "#techunboxing",
          "#reels"
        ],
        "publishedTime": "2024-09-20T15:34:44.000Z",
        "platform": "Instagram",
        "postType": "Video",
        "mediaUrl": "https://scontent-lga3-2.cdninstagram.com/v/t51.71878-15/504602138_1277055997321556_1125298810625313315_n.jpg?stp=dst-jpg_e35_p750x750_sh0.08_tt6&_nc_cat=109&ig_cache_key=MzQ2MTM1OTk3MDQ1NTA2NTM1MQ%3D%3D.3-ccb1-7&ccb=1-7&_nc_sid=58cdad&efg=eyJ2ZW5jb2RlX3RhZyI6InhwaWRzLjE1NjB4Mjc2OC5zZHIifQ%3D%3D&_nc_ohc=1wgmU40x1rsQ7kNvwFM8GC1&_nc_oc=AdmiSes81F6hWUQkrwD7wvvqE5LrT3mnMSFGFjfU_uhw-pGYi_JnqGFPoBFjGcHFD2U&_nc_ad=z-m&_nc_cid=0&_nc_zt=23&_nc_ht=scontent-lga3-2.cdninstagram.com&_nc_gid=vfruqG5mttwzjkDLoQkY0A&oh=00_AfQJ5_0ZdWXlFNsf8H0pFiNrinVe5mL-CKMkbRRrC435VA&oe=6883D82E",
        "postId": "3461359970455065351_17540369",
        "shortCode": "DAJOI3WuxMH",
        "ownerUsername": "karlconrad",
        "ownerFullName": "Karl Conrad",
        "ownerId": 17540369,
        "enhancementStatus": "completed"
      },
      {
        "creator": {
          "name": "Trendy&Trust",
          "uniqueId": "trendyntrust",
          "followers": 1404,
          "avatarUrl": "https://scontent-lga3-3.cdninstagram.com/v/t51.2885-19/517996165_17876852862362552_256704013131261612_n.jpg?stp=dst-jpg_e0_s150x150_tt6&_nc_ht=scontent-lga3-3.cdninstagram.com&_nc_cat=108&_nc_oc=Q6cZ2QG5_V1AFFHCiZSUWU0qq3jNsVTGP0DQJkT8rVfDrmdo3slyiLIcBRmpuO-HDWyhuqA&_nc_ohc=VuhgGA1bR60Q7kNvwFEdjnq&_nc_gid=vfruqG5mttwzjkDLoQkY0A&edm=AL2I2h8BAAAA&ccb=7-5&ig_cache_key=GIX_3x64I5Ao54I-AKwmG5vw-o8DbmNDAQAB-ccb7-5&oh=00_AfT0vaQDWMIkIhq2gb1J2aCd85n2yxsP4OQrDA4eB1pRrQ&oe=6883D943&_nc_sid=026283",
          "profilePicUrl": "https://scontent-lga3-3.cdninstagram.com/v/t51.2885-19/517996165_17876852862362552_256704013131261612_n.jpg?stp=dst-jpg_e0_s150x150_tt6&_nc_ht=scontent-lga3-3.cdninstagram.com&_nc_cat=108&_nc_oc=Q6cZ2QG5_V1AFFHCiZSUWU0qq3jNsVTGP0DQJkT8rVfDrmdo3slyiLIcBRmpuO-HDWyhuqA&_nc_ohc=VuhgGA1bR60Q7kNvwFEdjnq&_nc_gid=vfruqG5mttwzjkDLoQkY0A&edm=AL2I2h8BAAAA&ccb=7-5&ig_cache_key=GIX_3x64I5Ao54I-AKwmG5vw-o8DbmNDAQAB-ccb7-5&oh=00_AfT0vaQDWMIkIhq2gb1J2aCd85n2yxsP4OQrDA4eB1pRrQ&oe=6883D943&_nc_sid=026283",
          "verified": true,
          "bio": "Where Trends Meet Trust ✨  \nHigh-quality products since 2002 🛍️  \nDelivery all over Lebanon 🇱🇧  \nEasy exchange policy 🔄  \nShop now!",
          "emails": [],
          "qualityScore": 1075,
          "engagementRate": 0
        },
        "video": {
          "description": "Looking for premium Apple earbuds? 🍏\n- Waterproof, 24-hour battery life, and wired charging. 🔋 \n- Active Noise Cancellation (ANC) for an immersive audio experience. 🎧 \n- Compatible with both Apple and Android devices. 📱",
          "url": "https://www.instagram.com/reel/DKHGQjiM0Em",
          "statistics": {
            "likes": 12,
            "comments": 1,
            "views": 26102,
            "shares": 0
          }
        },
        "hashtags": [],
        "publishedTime": "2025-05-26T08:58:22.000Z",
        "platform": "Instagram",
        "postType": "Video",
        "mediaUrl": "https://scontent-lga3-2.cdninstagram.com/v/t51.71878-15/501351167_662904276569475_1310771320910227555_n.jpg?stp=dst-jpg_e15_tt6&_nc_cat=101&ig_cache_key=MzY0MDkwNjM0OTY5Nzc3Nzk1OA%3D%3D.3-ccb1-7&ccb=1-7&_nc_sid=58cdad&efg=eyJ2ZW5jb2RlX3RhZyI6InhwaWRzLjY0MHgxMTM2LnNkciJ9&_nc_ohc=qlQANTMCbdEQ7kNvwGZUqPF&_nc_oc=AdnTGz82fLbKGtd3ztU4fymzQb4OxJo03aYfbDUYKh9Ql5mhKU_2TjsMSy9Afdl3McI&_nc_ad=z-m&_nc_cid=0&_nc_zt=23&_nc_ht=scontent-lga3-2.cdninstagram.com&_nc_gid=vfruqG5mttwzjkDLoQkY0A&oh=00_AfSd9cgxKMwgnyAbFnmoO6BBZT5ETvMezROKqT6YjfaIzA&oe=6883D162",
        "postId": "3640906349697777958_70944162551",
        "shortCode": "DKHGQjiM0Em",
        "ownerUsername": "trendyntrust",
        "ownerFullName": "Trendy&Trust",
        "ownerId": 70944162551,
        "enhancementStatus": "completed"
      },
      {
        "creator": {
          "name": "Danny Winget",
          "uniqueId": "superscientific",
          "followers": 442443,
          "avatarUrl": "https://scontent-lga3-1.cdninstagram.com/v/t51.2885-19/92993151_559775617985766_5484175978563371008_n.jpg?stp=dst-jpg_e0_s150x150_tt6&_nc_ht=scontent-lga3-1.cdninstagram.com&_nc_cat=1&_nc_oc=Q6cZ2QG5_V1AFFHCiZSUWU0qq3jNsVTGP0DQJkT8rVfDrmdo3slyiLIcBRmpuO-HDWyhuqA&_nc_ohc=J9SGLoz40zsQ7kNvwFIhBmu&_nc_gid=vfruqG5mttwzjkDLoQkY0A&edm=AL2I2h8BAAAA&ccb=7-5&ig_cache_key=GH-2igXmLN3qHP0BAAAAAAD-tBtMbkULAAAB-ccb7-5&oh=00_AfTamoUsrQAf6juFqqOhNL5phfeGZk1HUEWSS8c-CE21dA&oe=6883F8F0&_nc_sid=026283",
          "profilePicUrl": "https://scontent-lga3-1.cdninstagram.com/v/t51.2885-19/92993151_559775617985766_5484175978563371008_n.jpg?stp=dst-jpg_e0_s150x150_tt6&_nc_ht=scontent-lga3-1.cdninstagram.com&_nc_cat=1&_nc_oc=Q6cZ2QG5_V1AFFHCiZSUWU0qq3jNsVTGP0DQJkT8rVfDrmdo3slyiLIcBRmpuO-HDWyhuqA&_nc_ohc=J9SGLoz40zsQ7kNvwFIhBmu&_nc_gid=vfruqG5mttwzjkDLoQkY0A&edm=AL2I2h8BAAAA&ccb=7-5&ig_cache_key=GH-2igXmLN3qHP0BAAAAAAD-tBtMbkULAAAB-ccb7-5&oh=00_AfTamoUsrQAf6juFqqOhNL5phfeGZk1HUEWSS8c-CE21dA&oe=6883F8F0&_nc_sid=026283",
          "verified": true,
          "bio": "Content Creator. Unboxing all things Tech with a mix of Travel + Family. www.youtube.com/dannywinget \nBusiness inquiries: superscientific@gmail.com",
          "emails": [
            "superscientific@gmail.com"
          ],
          "qualityScore": 1075,
          "engagementRate": 0
        },
        "video": {
          "description": "Apple AirPods 4 vs AirPods 4 ANC Unboxing! Which one would you rather have? The AirPods 4 are $129 and the AirPods 4 with ANC cost $179. For $50 more you get Active Noise Cancelation, Transparency Mode, Personalized Volume, Conversation Awareness, Speaker in the case for Find My and Wireless Charging. Is this a no brainer or is the improved audio of the H2 chip and redesigned fit enough for these wireless headphones/earbuds? Perfect companion for the iPhone 16 and iPhone 16 Pro Max? #tech #technology #apple #airpods4 #airpods4anc #unboxing #audio #wireless #headphones #earbuds #airpods #case #iphone16 #iphone16pro #iphone16promax #reels #reelsinstagram",
          "url": "https://www.instagram.com/reel/C_-h_dcuWpC",
          "statistics": {
            "likes": 1513,
            "comments": 28,
            "views": 66214,
            "shares": 0
          }
        },
        "hashtags": [
          "#tech",
          "#technology",
          "#apple",
          "#airpods4",
          "#airpods4anc",
          "#unboxing",
          "#audio",
          "#wireless",
          "#headphones",
          "#earbuds",
          "#airpods",
          "#case",
          "#iphone16",
          "#iphone16pro",
          "#iphone16promax",
          "#reels",
          "#reelsinstagram"
        ],
        "publishedTime": "2024-09-16T12:00:09.000Z",
        "platform": "Instagram",
        "postType": "Video",
        "mediaUrl": "https://scontent-lga3-3.cdninstagram.com/v/t51.71878-15/506312415_1492648898782758_7517591960536148972_n.jpg?stp=dst-jpg_e15_tt6&_nc_cat=110&ig_cache_key=MzQ1ODM1MTA2MDM0OTQ0NjcyMjE0OTI2NDg4OTU0NDk0MjU%3D.3-ccb1-7&ccb=1-7&_nc_sid=58cdad&efg=eyJ2ZW5jb2RlX3RhZyI6InhwaWRzLjcyMHgxMjgwLnNkciJ9&_nc_ohc=vOoIgGk5hK0Q7kNvwHS1VeN&_nc_oc=AdnfeuYE6XIitaw-RdYkp6OgKI0rrdjnsTwwd0d7nJhln5o9zT2FAwu9Lvor7_kCV-I&_nc_ad=z-m&_nc_cid=0&_nc_zt=23&_nc_ht=scontent-lga3-3.cdninstagram.com&_nc_gid=vfruqG5mttwzjkDLoQkY0A&oh=00_AfR1i8DKLDGY7KgDyiNLryHP_PvCkC48WvGqfEqQbONEmQ&oe=6883D12C",
        "postId": "3458351060349446722_236256359",
        "shortCode": "C_-h_dcuWpC",
        "ownerUsername": "superscientific",
        "ownerFullName": "Danny Winget",
        "ownerId": 236256359,
        "enhancementStatus": "completed"
      },
      {
        "creator": {
          "name": "CNET",
          "uniqueId": "cnet",
          "followers": 1305684,
          "avatarUrl": "https://scontent-lga3-3.cdninstagram.com/v/t51.2885-19/440695868_1163279305114036_3969876319015837235_n.jpg?stp=dst-jpg_e0_s150x150_tt6&_nc_ht=scontent-lga3-3.cdninstagram.com&_nc_cat=104&_nc_oc=Q6cZ2QG5_V1AFFHCiZSUWU0qq3jNsVTGP0DQJkT8rVfDrmdo3slyiLIcBRmpuO-HDWyhuqA&_nc_ohc=p6Hme5n4TWUQ7kNvwH6bv7I&_nc_gid=vfruqG5mttwzjkDLoQkY0A&edm=AL2I2h8BAAAA&ccb=7-5&ig_cache_key=GDx8RBq0gcER-yEEADOeLJV61Rc3bkULAAAB-ccb7-5&oh=00_AfTqIYEVh1eL6v9sVzkKzmJhtYzKX3_ZOE-VIuSrmGzGKw&oe=6883DF29&_nc_sid=026283",
          "profilePicUrl": "https://scontent-lga3-3.cdninstagram.com/v/t51.2885-19/440695868_1163279305114036_3969876319015837235_n.jpg?stp=dst-jpg_e0_s150x150_tt6&_nc_ht=scontent-lga3-3.cdninstagram.com&_nc_cat=104&_nc_oc=Q6cZ2QG5_V1AFFHCiZSUWU0qq3jNsVTGP0DQJkT8rVfDrmdo3slyiLIcBRmpuO-HDWyhuqA&_nc_ohc=p6Hme5n4TWUQ7kNvwH6bv7I&_nc_gid=vfruqG5mttwzjkDLoQkY0A&edm=AL2I2h8BAAAA&ccb=7-5&ig_cache_key=GDx8RBq0gcER-yEEADOeLJV61Rc3bkULAAAB-ccb7-5&oh=00_AfTqIYEVh1eL6v9sVzkKzmJhtYzKX3_ZOE-VIuSrmGzGKw&oe=6883DF29&_nc_sid=026283",
          "verified": true,
          "bio": "Your guide to a better future.",
          "emails": [],
          "qualityScore": 1075,
          "engagementRate": 0
        },
        "video": {
          "description": "We promise you these aren’t the 3rd Gen AirPods. #unboxing #samsung #apple #galaxybuds #earbuds #tech",
          "url": "https://www.instagram.com/reel/C9QambLPDrY",
          "statistics": {
            "likes": 675,
            "comments": 18,
            "views": 50329,
            "shares": 0
          }
        },
        "hashtags": [
          "#unboxing",
          "#samsung",
          "#apple",
          "#galaxybuds",
          "#earbuds",
          "#tech"
        ],
        "publishedTime": "2024-07-10T21:00:00.000Z",
        "platform": "Instagram",
        "postType": "Video",
        "mediaUrl": "https://scontent-lga3-2.cdninstagram.com/v/t51.71878-15/503044413_712829081682411_3858631500805311818_n.jpg?stp=dst-jpg_e35_p750x750_sh0.08_tt6&_nc_cat=105&ig_cache_key=MzQwOTM0MTkwNzY0ODM5NTk5Mg%3D%3D.3-ccb1-7&ccb=1-7&_nc_sid=58cdad&efg=eyJ2ZW5jb2RlX3RhZyI6InhwaWRzLjEwODB4MTkyMC5zZHIifQ%3D%3D&_nc_ohc=VrtwXUE2LlIQ7kNvwHRqcAK&_nc_oc=Adli0z90tKnEcMxFyTOuOGIFZM1OTtfoIlD6Dh4ZiS_034gxWZ3hfmMMrbW7Utj4MgA&_nc_ad=z-m&_nc_cid=0&_nc_zt=23&_nc_ht=scontent-lga3-2.cdninstagram.com&_nc_gid=vfruqG5mttwzjkDLoQkY0A&oh=00_AfTB7NPsRQEgdKn6YbhE8dADf04VdrElUYJwMN61pYVIxQ&oe=6883D98F",
        "postId": "3409341907648395992_6169156",
        "shortCode": "C9QambLPDrY",
        "ownerUsername": "cnet",
        "ownerFullName": "CNET",
        "ownerId": 6169156,
        "enhancementStatus": "completed"
      },
      {
        "creator": {
          "name": "Nathan Espinoza",
          "uniqueId": "nathanespinozayt",
          "followers": 181408,
          "avatarUrl": "https://scontent-lga3-1.cdninstagram.com/v/t51.2885-19/367511903_1002073357498120_7746375404560277844_n.jpg?stp=dst-jpg_e0_s150x150_tt6&_nc_ht=scontent-lga3-1.cdninstagram.com&_nc_cat=1&_nc_oc=Q6cZ2QG5_V1AFFHCiZSUWU0qq3jNsVTGP0DQJkT8rVfDrmdo3slyiLIcBRmpuO-HDWyhuqA&_nc_ohc=lG-zRDvI-44Q7kNvwHkCwF7&_nc_gid=vfruqG5mttwzjkDLoQkY0A&edm=AL2I2h8BAAAA&ccb=7-5&ig_cache_key=GF-J5xUIN4NiYY8DAFRho21jp4BrbkULAAAB-ccb7-5&oh=00_AfQQLUjgWwhKm3Hf1xjrWyvql53kxLgtOU2KYNDJpai0aw&oe=6883D008&_nc_sid=026283",
          "profilePicUrl": "https://scontent-lga3-1.cdninstagram.com/v/t51.2885-19/367511903_1002073357498120_7746375404560277844_n.jpg?stp=dst-jpg_e0_s150x150_tt6&_nc_ht=scontent-lga3-1.cdninstagram.com&_nc_cat=1&_nc_oc=Q6cZ2QG5_V1AFFHCiZSUWU0qq3jNsVTGP0DQJkT8rVfDrmdo3slyiLIcBRmpuO-HDWyhuqA&_nc_ohc=lG-zRDvI-44Q7kNvwHkCwF7&_nc_gid=vfruqG5mttwzjkDLoQkY0A&edm=AL2I2h8BAAAA&ccb=7-5&ig_cache_key=GF-J5xUIN4NiYY8DAFRho21jp4BrbkULAAAB-ccb7-5&oh=00_AfQQLUjgWwhKm3Hf1xjrWyvql53kxLgtOU2KYNDJpai0aw&oe=6883D008&_nc_sid=026283",
          "verified": true,
          "bio": "†\n20\ntech, gadgets, and stuff\nnathanespinoza@rakugomedia.com",
          "emails": [
            "nathanespinoza@rakugomedia.com"
          ],
          "qualityScore": 1075,
          "engagementRate": 0
        },
        "video": {
          "description": "Is this better than buying a whole new pair of earbuds?\n\n#tech #technology #gadgets #apple #airpods",
          "url": "https://www.instagram.com/reel/DMEVESDxyAG",
          "statistics": {
            "likes": 26925,
            "comments": 106,
            "views": 801972,
            "shares": 0
          }
        },
        "hashtags": [
          "#tech",
          "#technology",
          "#gadgets",
          "#apple",
          "#airpods"
        ],
        "publishedTime": "2025-07-14T00:13:18.000Z",
        "platform": "Instagram",
        "postType": "Video",
        "mediaUrl": "https://scontent-lga3-3.cdninstagram.com/v/t51.71878-15/518740669_1626348394724021_8008794126007930044_n.jpg?stp=dst-jpg_e15_tt6&_nc_cat=110&ig_cache_key=MzY3NjE1NTg0OTA4NjU0MTgzMA%3D%3D.3-ccb1-7&ccb=1-7&_nc_sid=58cdad&efg=eyJ2ZW5jb2RlX3RhZyI6InhwaWRzLjY0MHgxMTM2LnNkciJ9&_nc_ohc=2Y-lqHe0p8wQ7kNvwFNwKN0&_nc_oc=AdnSgAROvGTLk5pb-7qeH4WNOeq0N3Kx-0R6JURI72p3lFVTcNJqkRdtqXIyToX4wVE&_nc_ad=z-m&_nc_cid=0&_nc_zt=23&_nc_ht=scontent-lga3-3.cdninstagram.com&_nc_gid=vfruqG5mttwzjkDLoQkY0A&oh=00_AfT2AOmyz3IKm0_Jm_UBKGJiTwVTvMIIys6zwZWcSUX0Uw&oe=6883D862",
        "postId": "3676155849086541830_53648492227",
        "shortCode": "DMEVESDxyAG",
        "ownerUsername": "nathanespinozayt",
        "ownerFullName": "Nathan Espinoza",
        "ownerId": 53648492227,
        "enhancementStatus": "completed"
      },
      {
        "creator": {
          "name": "GadgetXpress",
          "uniqueId": "gadgetxpress_india",
          "followers": 1040,
          "avatarUrl": "https://scontent-lga3-2.cdninstagram.com/v/t51.2885-19/491893705_17866795155366257_4522301669594331921_n.jpg?stp=dst-jpg_e0_s150x150_tt6&_nc_ht=scontent-lga3-2.cdninstagram.com&_nc_cat=105&_nc_oc=Q6cZ2QG5_V1AFFHCiZSUWU0qq3jNsVTGP0DQJkT8rVfDrmdo3slyiLIcBRmpuO-HDWyhuqA&_nc_ohc=9c_qm1B1KlMQ7kNvwFAjuOl&_nc_gid=vfruqG5mttwzjkDLoQkY0A&edm=AL2I2h8BAAAA&ccb=7-5&ig_cache_key=GMmzUR1xoYJqwXk-ABF7U4doccI_bvEnAQAB-ccb7-5&oh=00_AfQgEYrexVRdyL8LBrfTt1FXJeguoJZy6WsTefsk3SABeA&oe=6883DD06&_nc_sid=026283",
          "profilePicUrl": "https://scontent-lga3-2.cdninstagram.com/v/t51.2885-19/491893705_17866795155366257_4522301669594331921_n.jpg?stp=dst-jpg_e0_s150x150_tt6&_nc_ht=scontent-lga3-2.cdninstagram.com&_nc_cat=105&_nc_oc=Q6cZ2QG5_V1AFFHCiZSUWU0qq3jNsVTGP0DQJkT8rVfDrmdo3slyiLIcBRmpuO-HDWyhuqA&_nc_ohc=9c_qm1B1KlMQ7kNvwFAjuOl&_nc_gid=vfruqG5mttwzjkDLoQkY0A&edm=AL2I2h8BAAAA&ccb=7-5&ig_cache_key=GMmzUR1xoYJqwXk-ABF7U4doccI_bvEnAQAB-ccb7-5&oh=00_AfQgEYrexVRdyL8LBrfTt1FXJeguoJZy6WsTefsk3SABeA&oe=6883DD06&_nc_sid=026283",
          "verified": false,
          "bio": "Websit link 👉http://gadgetxpress.in\n*Wholesale and retail*\nDM/WhatsApp👉7240688392\nCash on delivery available \nShipping all over india",
          "emails": [],
          "qualityScore": 75,
          "engagementRate": 0
        },
        "video": {
          "description": "APPLE EARBUDS\nPRICE.999/-\nCONTACT.7240688392,8290569898\n(Free delivery)\nCash on delivery available✅\nReturn and refund available✅\n#trendingreels #instadaily #applemusic\n#earbuds",
          "url": "https://www.instagram.com/reel/DLnBsu8v3eT",
          "statistics": {
            "likes": 11,
            "comments": 0,
            "views": 540,
            "shares": 0
          }
        },
        "hashtags": [
          "#trendingreels",
          "#instadaily",
          "#applemusic",
          "#earbuds"
        ],
        "publishedTime": "2025-07-02T15:07:19.000Z",
        "platform": "Instagram",
        "postType": "Video",
        "mediaUrl": "https://scontent-lga3-1.cdninstagram.com/v/t51.82787-15/514394009_17875301448366257_174886779440736722_n.jpg?stp=dst-jpg_e15_tt6&_nc_cat=103&ig_cache_key=MzY2NzkwNzg5MzYzMTM1MDY3NQ%3D%3D.3-ccb1-7&ccb=1-7&_nc_sid=58cdad&efg=eyJ2ZW5jb2RlX3RhZyI6InhwaWRzLjQ4MHg4NTQuc2RyIn0%3D&_nc_ohc=q81QZXJapsQQ7kNvwEwS3W-&_nc_oc=Adl490-4dp42pcznMwYCOObSfNeid4xfUm1iWtO9ohRF2hCKB95LfYu4naghKP1n0B8&_nc_ad=z-m&_nc_cid=0&_nc_zt=23&_nc_ht=scontent-lga3-1.cdninstagram.com&_nc_gid=vfruqG5mttwzjkDLoQkY0A&oh=00_AfTL5q3k8dEledMo0INgQ5cYfE46UaLcOJDUgQTTvgTWYQ&oe=6883D0D4",
        "postId": "3667907893631350675_70903822256",
        "shortCode": "DLnBsu8v3eT",
        "ownerUsername": "gadgetxpress_india",
        "ownerFullName": "GadgetXpress",
        "ownerId": 70903822256,
        "enhancementStatus": "completed"
      },
      {
        "creator": {
          "name": "ZahComputers.pk",
          "uniqueId": "zahcomputers.pk",
          "followers": 33796,
          "avatarUrl": "https://scontent-lga3-2.cdninstagram.com/v/t51.2885-19/120540838_136209948186265_171263691679934829_n.jpg?stp=dst-jpg_e0_s150x150_tt6&_nc_ht=scontent-lga3-2.cdninstagram.com&_nc_cat=101&_nc_oc=Q6cZ2QG5_V1AFFHCiZSUWU0qq3jNsVTGP0DQJkT8rVfDrmdo3slyiLIcBRmpuO-HDWyhuqA&_nc_ohc=qxexP_fvLD4Q7kNvwEimYqg&_nc_gid=vfruqG5mttwzjkDLoQkY0A&edm=AL2I2h8BAAAA&ccb=7-5&ig_cache_key=GKZOLweZlpPZ4XsAAG0pgZFrc2ACbkULAAAB-ccb7-5&oh=00_AfR73KRisHvHv0P8UefQ2goR72EIzXUXGhtef-Cs0ZQMyA&oe=6884000A&_nc_sid=026283",
          "profilePicUrl": "https://scontent-lga3-2.cdninstagram.com/v/t51.2885-19/120540838_136209948186265_171263691679934829_n.jpg?stp=dst-jpg_e0_s150x150_tt6&_nc_ht=scontent-lga3-2.cdninstagram.com&_nc_cat=101&_nc_oc=Q6cZ2QG5_V1AFFHCiZSUWU0qq3jNsVTGP0DQJkT8rVfDrmdo3slyiLIcBRmpuO-HDWyhuqA&_nc_ohc=qxexP_fvLD4Q7kNvwEimYqg&_nc_gid=vfruqG5mttwzjkDLoQkY0A&edm=AL2I2h8BAAAA&ccb=7-5&ig_cache_key=GKZOLweZlpPZ4XsAAG0pgZFrc2ACbkULAAAB-ccb7-5&oh=00_AfR73KRisHvHv0P8UefQ2goR72EIzXUXGhtef-Cs0ZQMyA&oe=6884000A&_nc_sid=026283",
          "verified": false,
          "bio": "Pakistan's #1 store for gaming & professional monitors.\nWith the largest inventory & trusted since 2012, we offer latest tech at competitive prices.",
          "emails": [],
          "qualityScore": 75,
          "engagementRate": 0
        },
        "video": {
          "description": "Apple MXP93 AirPods 4th Gen Noise-Canceling Earbuds with USB-C Charging Case\n\n☑️ For iPhone, Apple Watch, iPad, and Mac\n☑️ Active Noise Canceling with 3 Modes\n☑️ Spatial Audio with Dynamic Head Tracking\n☑️ H2 Chip for Intelligent Functions\n☑️ IP54 Dust, Sweat, and Water Resistant\n☑️ Up to 30 Hours of Playback with Case\n☑️ Voice Isolation for Clear Calls\n☑️ Force Sensor for Audio/Calls Control\n☑️ Enhanced Acoustic Architecture\n☑️ Includes Wireless Charging Case\n\nOrder Here:\nhttps://ln.run/69m6p\n\n📍 Store Location:\nShop #GC51, Technocity Mall, I.I. Chundrigar Rd, Karachi\n\n🚚📦 Nationwide Delivery:\nWe offer COD delivery services throughout Pakistan, along with same-day delivery options in Karachi.\n\nContact Us:\n📞 WhatsApp: 0321-5530993, 0325-7033554\n☎️ PTCL: 02132277661\n\n#Apple #MXP93 #AirPods #4thGen #NoiseCanceling #Earbuds\n#zahcomputer #zahcomputers",
          "url": "https://www.instagram.com/reel/DEhpmRjqnvZ",
          "statistics": {
            "likes": 57,
            "comments": 0,
            "views": 4624,
            "shares": 0
          }
        },
        "hashtags": [
          "#GC51",
          "#Apple",
          "#MXP93",
          "#AirPods",
          "#4thGen",
          "#NoiseCanceling",
          "#Earbuds",
          "#zahcomputer",
          "#zahcomputers"
        ],
        "publishedTime": "2025-01-07T13:19:04.000Z",
        "platform": "Instagram",
        "postType": "Video",
        "mediaUrl": "https://scontent-lga3-2.cdninstagram.com/v/t51.71878-15/503371650_4133244853665145_3023110276554606757_n.jpg?stp=dst-jpg_e15_tt6&_nc_cat=109&ig_cache_key=MzU0MDI5MzczMjE4ODk3ODEzNzQxMzMyNDQ4NDY5OTg0Nzk%3D.3-ccb1-7&ccb=1-7&_nc_sid=58cdad&efg=eyJ2ZW5jb2RlX3RhZyI6InhwaWRzLjcyMHgxMjgwLnNkciJ9&_nc_ohc=yZzN_sTBOsYQ7kNvwHK8Cer&_nc_oc=AdkO15EXmWJNT3CH8qHTCZUSLDyZm3b2skXLzhT-CYRAR6WIasJBP-yYrcG1LNE8_sk&_nc_ad=z-m&_nc_cid=0&_nc_zt=23&_nc_ht=scontent-lga3-2.cdninstagram.com&_nc_gid=vfruqG5mttwzjkDLoQkY0A&oh=00_AfT83DAzofpWAT24pqcTOfFTLZV7P_QE7Ob7GblYUaVIOQ&oe=6883E1E3",
        "postId": "3540293732188978137_42664820025",
        "shortCode": "DEhpmRjqnvZ",
        "ownerUsername": "zahcomputers.pk",
        "ownerFullName": "ZahComputers.pk",
        "ownerId": 42664820025,
        "enhancementStatus": "completed"
      },
      {
        "creator": {
          "name": "Gadgets Bazaar",
          "uniqueId": "2024gadgetsbazaar",
          "followers": 4403,
          "avatarUrl": "https://scontent-lga3-3.cdninstagram.com/v/t51.2885-19/446347529_4147570858717246_4114923860429331272_n.jpg?stp=dst-jpg_e0_s150x150_tt6&_nc_ht=scontent-lga3-3.cdninstagram.com&_nc_cat=110&_nc_oc=Q6cZ2QG5_V1AFFHCiZSUWU0qq3jNsVTGP0DQJkT8rVfDrmdo3slyiLIcBRmpuO-HDWyhuqA&_nc_ohc=0UfW8gkr6uoQ7kNvwH_YtNg&_nc_gid=vfruqG5mttwzjkDLoQkY0A&edm=AL2I2h8BAAAA&ccb=7-5&ig_cache_key=GAm5mho_8LaXMbwOAEhbqwJzJRs5bkULAAAB-ccb7-5&oh=00_AfR2iNqsEaN5UCuXq4Ro-w7c3xL0lQsYyigWebegqKuKaA&oe=6883FD85&_nc_sid=026283",
          "profilePicUrl": "https://scontent-lga3-3.cdninstagram.com/v/t51.2885-19/446347529_4147570858717246_4114923860429331272_n.jpg?stp=dst-jpg_e0_s150x150_tt6&_nc_ht=scontent-lga3-3.cdninstagram.com&_nc_cat=110&_nc_oc=Q6cZ2QG5_V1AFFHCiZSUWU0qq3jNsVTGP0DQJkT8rVfDrmdo3slyiLIcBRmpuO-HDWyhuqA&_nc_ohc=0UfW8gkr6uoQ7kNvwH_YtNg&_nc_gid=vfruqG5mttwzjkDLoQkY0A&edm=AL2I2h8BAAAA&ccb=7-5&ig_cache_key=GAm5mho_8LaXMbwOAEhbqwJzJRs5bkULAAAB-ccb7-5&oh=00_AfR2iNqsEaN5UCuXq4Ro-w7c3xL0lQsYyigWebegqKuKaA&oe=6883FD85&_nc_sid=026283",
          "verified": false,
          "bio": "🎧⌚️I Deals in smart gadgets\n🚚📦I All india delivery\n💬📨I wtsno.7566243621\n🏤🏣I main page:@immonishsiddiqui\n💰🤑| payment COD available\n🙅❌| no return&refund",
          "emails": [],
          "qualityScore": 75,
          "engagementRate": 0
        },
        "video": {
          "description": "Apple earbuds Pro 2 second generation cod available only 999 #apple #earbuds #buds #headphone #viral #song",
          "url": "https://www.instagram.com/reel/C7yVB9GM0F0",
          "statistics": {
            "likes": 3,
            "comments": 0,
            "views": 4901,
            "shares": 0
          }
        },
        "hashtags": [
          "#apple",
          "#earbuds",
          "#buds",
          "#headphone",
          "#viral",
          "#song"
        ],
        "publishedTime": "2024-06-04T08:05:11.000Z",
        "platform": "Instagram",
        "postType": "Video",
        "mediaUrl": "https://scontent-lga3-2.cdninstagram.com/v/t51.71878-15/503922796_2736879029834807_4271822565351499712_n.jpg?stp=dst-jpg_e35_p750x750_sh0.08_tt6&_nc_cat=109&ig_cache_key=MzM4Mjg1ODc2MzQwNzE0NzM4MA%3D%3D.3-ccb1-7&ccb=1-7&_nc_sid=58cdad&efg=eyJ2ZW5jb2RlX3RhZyI6InhwaWRzLjEwODB4MTkyMC5zZHIifQ%3D%3D&_nc_ohc=OaTcIggGMsEQ7kNvwGZTkjh&_nc_oc=Admr6y3DEVf_nghV_1MY5U8M8Q173TEuO_6n8Z--7pdbc6vEVzRxQBOGxf3Gbz4Gqd8&_nc_ad=z-m&_nc_cid=0&_nc_zt=23&_nc_ht=scontent-lga3-2.cdninstagram.com&_nc_gid=vfruqG5mttwzjkDLoQkY0A&oh=00_AfRwaiP-W0QNpGE9wncLSmYuv71Te90Q6baHb_ojgJDQiQ&oe=6883F1D1",
        "postId": "3382858763407147380_64095945188",
        "shortCode": "C7yVB9GM0F0",
        "ownerUsername": "2024gadgetsbazaar",
        "ownerFullName": "Gadgets Bazaar",
        "ownerId": 64095945188,
        "enhancementStatus": "completed"
      },
      {
        "creator": {
          "name": "Miles Telecom Trading LLC",
          "uniqueId": "milestelecom",
          "followers": 6777,
          "avatarUrl": "https://scontent-lga3-2.cdninstagram.com/v/t51.2885-19/119604815_2770882909848453_3180782082853123946_n.jpg?stp=dst-jpg_e0_s150x150_tt6&_nc_ht=scontent-lga3-2.cdninstagram.com&_nc_cat=109&_nc_oc=Q6cZ2QG5_V1AFFHCiZSUWU0qq3jNsVTGP0DQJkT8rVfDrmdo3slyiLIcBRmpuO-HDWyhuqA&_nc_ohc=lukGOS88fCgQ7kNvwGHIQ2T&_nc_gid=vfruqG5mttwzjkDLoQkY0A&edm=AL2I2h8BAAAA&ccb=7-5&ig_cache_key=GE8GIQeFQ45zGtgJAGo3Y6xzaCQsbkULAAAB-ccb7-5&oh=00_AfQuVrkipBAFgSMVkF1jsLgp0PaWult8nCQhjCO0e1I-1w&oe=6883DF72&_nc_sid=026283",
          "profilePicUrl": "https://scontent-lga3-2.cdninstagram.com/v/t51.2885-19/119604815_2770882909848453_3180782082853123946_n.jpg?stp=dst-jpg_e0_s150x150_tt6&_nc_ht=scontent-lga3-2.cdninstagram.com&_nc_cat=109&_nc_oc=Q6cZ2QG5_V1AFFHCiZSUWU0qq3jNsVTGP0DQJkT8rVfDrmdo3slyiLIcBRmpuO-HDWyhuqA&_nc_ohc=lukGOS88fCgQ7kNvwGHIQ2T&_nc_gid=vfruqG5mttwzjkDLoQkY0A&edm=AL2I2h8BAAAA&ccb=7-5&ig_cache_key=GE8GIQeFQ45zGtgJAGo3Y6xzaCQsbkULAAAB-ccb7-5&oh=00_AfQuVrkipBAFgSMVkF1jsLgp0PaWult8nCQhjCO0e1I-1w&oe=6883DF72&_nc_sid=026283",
          "verified": false,
          "bio": "📱Your one-stop shop for the Latest\nMobiles | Gadgets | Accessories | Repair",
          "emails": [],
          "qualityScore": 75,
          "engagementRate": 0
        },
        "video": {
          "description": "Apple AirPods 4 & AirPods 4 ANC 😍\n\nAvailable in Miles Telecom \n\n➡ WhatsApp +971 56 711 5547\n\n🛍 For Buy Brand new Phone, Accessories & Gadgets visit our website: www.milestelecom.com\n\n📍 Al Satwa Road, Al Satwa, Dubai, UAE\n\n#apple #airpods4 #noisecancelling #noisecancellingheadphones #headphones #earbuds #wireless #trending #reelsviral #sound #iphone16promax #dubai #abudhabi #shoppingonline #foryou #fyp #foryoupage #explore #milestelecom",
          "url": "https://www.instagram.com/reel/DFIrDxNSKuw",
          "statistics": {
            "likes": 5,
            "comments": 0,
            "views": 1056,
            "shares": 0
          }
        },
        "hashtags": [
          "#apple",
          "#airpods4",
          "#noisecancelling",
          "#noisecancellingheadphones",
          "#headphones",
          "#earbuds",
          "#wireless",
          "#trending",
          "#reelsviral",
          "#sound",
          "#iphone16promax",
          "#dubai",
          "#abudhabi",
          "#shoppingonline",
          "#foryou",
          "#fyp",
          "#foryoupage",
          "#explore",
          "#milestelecom"
        ],
        "publishedTime": "2025-01-22T17:02:12.000Z",
        "platform": "Instagram",
        "postType": "Video",
        "mediaUrl": "https://scontent-lga3-2.cdninstagram.com/v/t51.75761-15/474816622_18460198780071562_3441716931186437485_n.jpg?stp=dst-jpg_e15_tt6&_nc_cat=100&ig_cache_key=MzU1MTI3NzY4MTE3NjI1OTUwNA%3D%3D.3-ccb1-7&ccb=1-7&_nc_sid=58cdad&efg=eyJ2ZW5jb2RlX3RhZyI6InhwaWRzLjcyMHgxMjgwLnNkciJ9&_nc_ohc=1FU1EBOjqCoQ7kNvwHFjOr9&_nc_oc=Adm7o1_9Uxj9TDntXwSpwutKNuFAkxNMWmpbz8wwfhUjMIAaavlRm6vTKj1sBTcDAzc&_nc_ad=z-m&_nc_cid=0&_nc_zt=23&_nc_ht=scontent-lga3-2.cdninstagram.com&_nc_gid=vfruqG5mttwzjkDLoQkY0A&oh=00_AfQSdML0Mn7vBPddofTsAiF2ZUQm1OH8sGmYV4zUApvENw&oe=6883D33C",
        "postId": "3551277681176259504_1926895561",
        "shortCode": "DFIrDxNSKuw",
        "ownerUsername": "milestelecom",
        "ownerFullName": "Miles Telecom Trading LLC",
        "ownerId": 1926895561,
        "enhancementStatus": "completed"
      },
      {
        "creator": {
          "name": "SmartGadgetCoach",
          "uniqueId": "smartgadgetcoach",
          "followers": 772,
          "avatarUrl": "https://scontent-lga3-1.cdninstagram.com/v/t51.2885-19/517316527_17935945464052391_4237941033794759677_n.jpg?stp=dst-jpg_e0_s150x150_tt6&_nc_ht=scontent-lga3-1.cdninstagram.com&_nc_cat=111&_nc_oc=Q6cZ2QG5_V1AFFHCiZSUWU0qq3jNsVTGP0DQJkT8rVfDrmdo3slyiLIcBRmpuO-HDWyhuqA&_nc_ohc=MHxX_cUW6DUQ7kNvwGdA98R&_nc_gid=vfruqG5mttwzjkDLoQkY0A&edm=AL2I2h8BAAAA&ccb=7-5&ig_cache_key=GK_f1R6nehi6pbg-AP1rY6rqMNA6bmNDAQAB-ccb7-5&oh=00_AfRoqcg6aOef27R9jK0yIHUOYIjSxL_hPE22UbYUGxrYqQ&oe=6883D64B&_nc_sid=026283",
          "profilePicUrl": "https://scontent-lga3-1.cdninstagram.com/v/t51.2885-19/517316527_17935945464052391_4237941033794759677_n.jpg?stp=dst-jpg_e0_s150x150_tt6&_nc_ht=scontent-lga3-1.cdninstagram.com&_nc_cat=111&_nc_oc=Q6cZ2QG5_V1AFFHCiZSUWU0qq3jNsVTGP0DQJkT8rVfDrmdo3slyiLIcBRmpuO-HDWyhuqA&_nc_ohc=MHxX_cUW6DUQ7kNvwGdA98R&_nc_gid=vfruqG5mttwzjkDLoQkY0A&edm=AL2I2h8BAAAA&ccb=7-5&ig_cache_key=GK_f1R6nehi6pbg-AP1rY6rqMNA6bmNDAQAB-ccb7-5&oh=00_AfRoqcg6aOef27R9jK0yIHUOYIjSxL_hPE22UbYUGxrYqQ&oe=6883D64B&_nc_sid=026283",
          "verified": false,
          "bio": "📦 Gadget Seller | 💰 Digital Coach  \n🎯 New eBook: ₹1L/month plan  \n👇 DM “START” for full guide",
          "emails": [],
          "qualityScore": 75,
          "engagementRate": 0
        },
        "video": {
          "description": "Apple earbuds<This one💀[Link in bio]\n.\n.\n.\n.\n.\n.\n.\n.\n#earbuds #appleearpods #smartearbuds #premium #viralreels #explorepage #trendingreels #omnimart #trendreels\n do you like this product?",
          "url": "https://www.instagram.com/reel/DLEciSHx_ti",
          "statistics": {
            "likes": 44,
            "comments": 5,
            "views": 1861,
            "shares": 0
          }
        },
        "hashtags": [
          "#earbuds",
          "#appleearpods",
          "#smartearbuds",
          "#premium",
          "#viralreels",
          "#explorepage",
          "#trendingreels",
          "#omnimart",
          "#trendreels"
        ],
        "publishedTime": "2025-06-19T04:52:55.000Z",
        "platform": "Instagram",
        "postType": "Video",
        "mediaUrl": "https://scontent-lga3-1.cdninstagram.com/v/t51.71878-15/502407044_1471596204274047_8534163554127194377_n.jpg?stp=dst-jpg_e15_tt6&_nc_cat=102&ig_cache_key=MzY1ODE3NDI5ODU1NDEwNDY3NA%3D%3D.3-ccb1-7&ccb=1-7&_nc_sid=58cdad&efg=eyJ2ZW5jb2RlX3RhZyI6InhwaWRzLjY0MHgxMTM2LnNkciJ9&_nc_ohc=SIBX_y-S8uUQ7kNvwHk1Tkz&_nc_oc=AdlqySWS3sOxmuNMg58Rwf06Rru3opL9hyUkAhUIFxRlLnMkRUyld_ymFq6_cIT-oxc&_nc_ad=z-m&_nc_cid=0&_nc_zt=23&_nc_ht=scontent-lga3-1.cdninstagram.com&_nc_gid=vfruqG5mttwzjkDLoQkY0A&oh=00_AfQnIsuRZ141i4rtTV5s3LScYzSvvxPX6EpsC_Ihr2BhjQ&oe=68840406",
        "postId": "3658174298554104674_61520508390",
        "shortCode": "DLEciSHx_ti",
        "ownerUsername": "smartgadgetcoach",
        "ownerFullName": "SmartGadgetCoach",
        "ownerId": 61520508390,
        "enhancementStatus": "completed"
      },
      {
        "creator": {
          "name": "Banjara Electronics",
          "uniqueId": "banjara_electronics",
          "followers": 19893,
          "avatarUrl": "https://scontent-lga3-3.cdninstagram.com/v/t51.2885-19/350249556_633013925387110_2731566931429399020_n.jpg?stp=dst-jpg_e0_s150x150_tt6&_nc_ht=scontent-lga3-3.cdninstagram.com&_nc_cat=110&_nc_oc=Q6cZ2QG5_V1AFFHCiZSUWU0qq3jNsVTGP0DQJkT8rVfDrmdo3slyiLIcBRmpuO-HDWyhuqA&_nc_ohc=p7IKWR61Jh8Q7kNvwFIGzLb&_nc_gid=vfruqG5mttwzjkDLoQkY0A&edm=AL2I2h8BAAAA&ccb=7-5&ig_cache_key=GFRi4BRmGykKuT8CAOyZDdSmeeglbkULAAAB-ccb7-5&oh=00_AfTdRzXYzSjIGhpQ23gCYo9ppom_o5bhH7okv4yx0igdrw&oe=6883F7DA&_nc_sid=026283",
          "profilePicUrl": "https://scontent-lga3-3.cdninstagram.com/v/t51.2885-19/350249556_633013925387110_2731566931429399020_n.jpg?stp=dst-jpg_e0_s150x150_tt6&_nc_ht=scontent-lga3-3.cdninstagram.com&_nc_cat=110&_nc_oc=Q6cZ2QG5_V1AFFHCiZSUWU0qq3jNsVTGP0DQJkT8rVfDrmdo3slyiLIcBRmpuO-HDWyhuqA&_nc_ohc=p7IKWR61Jh8Q7kNvwFIGzLb&_nc_gid=vfruqG5mttwzjkDLoQkY0A&edm=AL2I2h8BAAAA&ccb=7-5&ig_cache_key=GFRi4BRmGykKuT8CAOyZDdSmeeglbkULAAAB-ccb7-5&oh=00_AfTdRzXYzSjIGhpQ23gCYo9ppom_o5bhH7okv4yx0igdrw&oe=6883F7DA&_nc_sid=026283",
          "verified": false,
          "bio": "•We deal in all kind of electronics & accessories •Guaranteed 100% original •Amazon/Flipkart clearance inventory •Max Delivery time- 45days",
          "emails": [],
          "qualityScore": 75,
          "engagementRate": 0
        },
        "video": {
          "description": "Apple EarPods | Just for 999 | Banjara Electronics \n\n#apple #applemusic #earpods #earpod #earphones #earphoneiphone #iphone #appleiphone #itune #earbuds #under999 #gadgets #banjaraelectronics #houseofbanjara",
          "url": "https://www.instagram.com/reel/DIgB0CQRYkL",
          "statistics": {
            "likes": 38,
            "comments": 0,
            "views": 64733,
            "shares": 0
          }
        },
        "hashtags": [
          "#apple",
          "#applemusic",
          "#earpods",
          "#earpod",
          "#earphones",
          "#earphoneiphone",
          "#iphone",
          "#appleiphone",
          "#itune",
          "#earbuds",
          "#under999",
          "#gadgets",
          "#banjaraelectronics",
          "#houseofbanjara"
        ],
        "publishedTime": "2025-04-16T08:19:23.000Z",
        "platform": "Instagram",
        "postType": "Video",
        "mediaUrl": "https://scontent-lga3-2.cdninstagram.com/v/t51.75761-15/489850341_18083229985712333_8724639061241791363_n.jpg?stp=dst-jpg_e35_p750x750_sh0.08_tt6&_nc_cat=105&ig_cache_key=MzYxMTg5NDg3NTAzMDkxNTMzOQ%3D%3D.3-ccb1-7&ccb=1-7&_nc_sid=58cdad&efg=eyJ2ZW5jb2RlX3RhZyI6InhwaWRzLjMyMTZ4NTcxMi5zZHIifQ%3D%3D&_nc_ohc=NY-kOfMik1gQ7kNvwHHNA7B&_nc_oc=Adl0IGRJI8pgFGjjtXt_GVbUVgvuwXX-ie8rnGG5z6CUUfVANlBrx8l4B0jzmkuep4Q&_nc_ad=z-m&_nc_cid=0&_nc_zt=23&_nc_ht=scontent-lga3-2.cdninstagram.com&_nc_gid=vfruqG5mttwzjkDLoQkY0A&oh=00_AfS-8jUONKycQpm_QjEpNbMm3-z2WpJptUYlcGIYnFC6eQ&oe=6883F8A3",
        "postId": "3611894875030915339_21468952332",
        "shortCode": "DIgB0CQRYkL",
        "ownerUsername": "banjara_electronics",
        "ownerFullName": "Banjara Electronics",
        "ownerId": 21468952332,
        "enhancementStatus": "completed"
      },
      {
        "creator": {
          "name": "Mark Ellis",
          "uniqueId": "markellisreviews",
          "followers": 9395,
          "avatarUrl": "https://scontent-lga3-2.cdninstagram.com/v/t51.2885-19/106122814_724988331673128_204655154213389750_n.jpg?stp=dst-jpg_e0_s150x150_tt6&_nc_ht=scontent-lga3-2.cdninstagram.com&_nc_cat=100&_nc_oc=Q6cZ2QG5_V1AFFHCiZSUWU0qq3jNsVTGP0DQJkT8rVfDrmdo3slyiLIcBRmpuO-HDWyhuqA&_nc_ohc=rcFdNSTOiY4Q7kNvwFYwNg2&_nc_gid=vfruqG5mttwzjkDLoQkY0A&edm=AL2I2h8BAAAA&ccb=7-5&ig_cache_key=GD5OUwYoxvl-X5MCALaFV0jHFNcCbkULAAAB-ccb7-5&oh=00_AfR5CGc1xWEITMMawDuPVkOS9G8aMXa1xeId5G5qR39Gvg&oe=6883EFD4&_nc_sid=026283",
          "profilePicUrl": "https://scontent-lga3-2.cdninstagram.com/v/t51.2885-19/106122814_724988331673128_204655154213389750_n.jpg?stp=dst-jpg_e0_s150x150_tt6&_nc_ht=scontent-lga3-2.cdninstagram.com&_nc_cat=100&_nc_oc=Q6cZ2QG5_V1AFFHCiZSUWU0qq3jNsVTGP0DQJkT8rVfDrmdo3slyiLIcBRmpuO-HDWyhuqA&_nc_ohc=rcFdNSTOiY4Q7kNvwFYwNg2&_nc_gid=vfruqG5mttwzjkDLoQkY0A&edm=AL2I2h8BAAAA&ccb=7-5&ig_cache_key=GD5OUwYoxvl-X5MCALaFV0jHFNcCbkULAAAB-ccb7-5&oh=00_AfR5CGc1xWEITMMawDuPVkOS9G8aMXa1xeId5G5qR39Gvg&oe=6883EFD4&_nc_sid=026283",
          "verified": false,
          "bio": "Tech reviewer. Car reviewer. Might review you, if you stand still for too long.",
          "emails": [],
          "qualityScore": 75,
          "engagementRate": 0
        },
        "video": {
          "description": "What is the thing that makes you buy a pair of ear buds ? \n\nWould you spend the extra £100 ?\n\n#beats #beatsbydre #earbuds #beatssolobuds #apple",
          "url": "https://www.instagram.com/reel/C8pyrIEIJQd",
          "statistics": {
            "likes": 89,
            "comments": 3,
            "views": 5066,
            "shares": 0
          }
        },
        "hashtags": [
          "#beats",
          "#beatsbydre",
          "#earbuds",
          "#beatssolobuds",
          "#apple"
        ],
        "publishedTime": "2024-06-25T21:00:00.000Z",
        "platform": "Instagram",
        "postType": "Video",
        "mediaUrl": "https://scontent-lga3-1.cdninstagram.com/v/t51.71878-15/503011861_1375486787105756_4582163686592688591_n.jpg?stp=dst-jpg_e35_p750x750_sh0.08_tt6&_nc_cat=111&ig_cache_key=MzM5ODQ3MDI1OTc0OTk4MzI2MQ%3D%3D.3-ccb1-7&ccb=1-7&_nc_sid=58cdad&efg=eyJ2ZW5jb2RlX3RhZyI6InhwaWRzLjExNzB4MjA3Ni5zZHIifQ%3D%3D&_nc_ohc=10_3vSLwpAwQ7kNvwGmNYNd&_nc_oc=AdnbJgMh5dNlqAv7InZYTc10gXMMLXaUpL_eUtUK6yC8JeY0xkXExJ7P8QO4EX11AZw&_nc_ad=z-m&_nc_cid=0&_nc_zt=23&_nc_ht=scontent-lga3-1.cdninstagram.com&_nc_gid=vfruqG5mttwzjkDLoQkY0A&oh=00_AfS_lLDGrtv4-RyIkrJvoOWgSTRhvXOPIz-QBiNTcdVStA&oe=6883E359",
        "postId": "3398470259749983261_37019727395",
        "shortCode": "C8pyrIEIJQd",
        "ownerUsername": "markellisreviews",
        "ownerFullName": "Mark Ellis",
        "ownerId": 37019727395,
        "enhancementStatus": "completed"
      }
    ]
  }
}