{
  "timestamp": "2025-07-18T16:41:26.370Z",
  "platform": "instagram",
  "searchType": "keyword",
  "request": {
    "keywords": [
      "airpods pro"
    ],
    "targetResults": 100,
    "platform": "Instagram"
  },
  "response": {
    "items": [
      {
        "creator": {
          "name": "Sam Kohl",
          "uniqueId": "imsamkohl",
          "followers": 8474,
          "avatarUrl": "https://scontent-lax3-2.cdninstagram.com/v/t51.2885-19/450845122_494167976340851_5536232985279398246_n.jpg?stp=dst-jpg_e0_s150x150_tt6&_nc_ht=scontent-lax3-2.cdninstagram.com&_nc_cat=111&_nc_oc=Q6cZ2QGOVUycnKDu-w2BPgYicYzZQI0oAb3CdkjydDw_CmlZzb_EhX9DMymbDteU5Kw93xs&_nc_ohc=YPmllJ1U_IUQ7kNvwEbPBHW&_nc_gid=K5AjRxJ13kAgLaWaMGC1bQ&edm=AL2I2h8BAAAA&ccb=7-5&oh=00_AfRSf3qVHBZetaIJjG9fybpt8loXis_oi3ksPyS3rSLKKA&oe=68804924&_nc_sid=026283",
          "profilePicUrl": "https://scontent-lax3-2.cdninstagram.com/v/t51.2885-19/450845122_494167976340851_5536232985279398246_n.jpg?stp=dst-jpg_e0_s150x150_tt6&_nc_ht=scontent-lax3-2.cdninstagram.com&_nc_cat=111&_nc_oc=Q6cZ2QGOVUycnKDu-w2BPgYicYzZQI0oAb3CdkjydDw_CmlZzb_EhX9DMymbDteU5Kw93xs&_nc_ohc=YPmllJ1U_IUQ7kNvwEbPBHW&_nc_gid=K5AjRxJ13kAgLaWaMGC1bQ&edm=AL2I2h8BAAAA&ccb=7-5&oh=00_AfRSf3qVHBZetaIJjG9fybpt8loXis_oi3ksPyS3rSLKKA&oe=68804924&_nc_sid=026283",
          "verified": true,
          "bio": "Lead Apple shepherd @appltrack, inquires at hello@appletrack.com",
          "emails": [
            "hello@appletrack.com"
          ],
          "qualityScore": 1075,
          "engagementRate": 0
        },
        "video": {
          "description": "AirPods Pro 3 might not have stems #apple #airpods #rumors",
          "url": "https://www.instagram.com/reel/DMFU-a9u8cp",
          "statistics": {
            "likes": 3178,
            "comments": 20,
            "views": 89206,
            "shares": 0
          }
        },
        "hashtags": [
          "#apple",
          "#airpods",
          "#rumors"
        ],
        "publishedTime": "2025-07-14T09:31:46.000Z",
        "platform": "Instagram",
        "postType": "Video",
        "mediaUrl": "https://scontent-lax3-2.cdninstagram.com/v/t51.71878-15/519411991_1915464112581893_8258031037878199285_n.jpg?stp=dst-jpg_e15_tt6&_nc_cat=1&ig_cache_key=MzY3NjQzNjkyMTMwODY2MTU0NQ%3D%3D.3-ccb1-7&ccb=1-7&_nc_sid=58cdad&efg=eyJ2ZW5jb2RlX3RhZyI6InhwaWRzLjY0MHgxMTM2LnNkciJ9&_nc_ohc=3hjlckuuc3cQ7kNvwFJ8890&_nc_oc=Adl7Z0SzQOwKGg79GGWlEc0AD0cT3DLWqUP5rRuP7h1uHOwC7rezHSSVHw6T_xIq-8Q&_nc_ad=z-m&_nc_cid=0&_nc_zt=23&_nc_ht=scontent-lax3-2.cdninstagram.com&_nc_gid=K5AjRxJ13kAgLaWaMGC1bQ&oh=00_AfQMMbyhk7f3GH03KN1akIQoM4NfG8yT7B3vLczEhGoLag&oe=68804E45",
        "postId": "3676436921308661545_9003918521",
        "shortCode": "DMFU-a9u8cp",
        "ownerUsername": "imsamkohl",
        "ownerFullName": "Sam Kohl",
        "ownerId": 9003918521,
        "enhancementStatus": "completed"
      },
      {
        "creator": {
          "name": "PHONE VENDOR - phones📱laptops 💻 games 🎮 accessories 🔌",
          "uniqueId": "phonesvendor",
          "followers": 135494,
          "avatarUrl": "https://scontent-lax3-1.cdninstagram.com/v/t51.2885-19/468080954_1248456376484777_2089239628641208632_n.jpg?stp=dst-jpg_e0_s150x150_tt6&_nc_ht=scontent-lax3-1.cdninstagram.com&_nc_cat=105&_nc_oc=Q6cZ2QGOVUycnKDu-w2BPgYicYzZQI0oAb3CdkjydDw_CmlZzb_EhX9DMymbDteU5Kw93xs&_nc_ohc=M5XOTvpsNhwQ7kNvwGjsb-K&_nc_gid=K5AjRxJ13kAgLaWaMGC1bQ&edm=AL2I2h8BAAAA&ccb=7-5&oh=00_AfT_WVmwS6y3GQj3TySpRDM2yONHaUGqrog6r5uysExVDA&oe=68804135&_nc_sid=026283",
          "profilePicUrl": "https://scontent-lax3-1.cdninstagram.com/v/t51.2885-19/468080954_1248456376484777_2089239628641208632_n.jpg?stp=dst-jpg_e0_s150x150_tt6&_nc_ht=scontent-lax3-1.cdninstagram.com&_nc_cat=105&_nc_oc=Q6cZ2QGOVUycnKDu-w2BPgYicYzZQI0oAb3CdkjydDw_CmlZzb_EhX9DMymbDteU5Kw93xs&_nc_ohc=M5XOTvpsNhwQ7kNvwGjsb-K&_nc_gid=K5AjRxJ13kAgLaWaMGC1bQ&edm=AL2I2h8BAAAA&ccb=7-5&oh=00_AfT_WVmwS6y3GQj3TySpRDM2yONHaUGqrog6r5uysExVDA&oe=68804135&_nc_sid=026283",
          "verified": true,
          "bio": "- Your reliable source for all things tech!\n- Smartphones, laptops, games & accessories\n- 08035347560 | 08059091113 | 07013222030",
          "emails": [],
          "qualityScore": 1075,
          "engagementRate": 0
        },
        "video": {
          "description": "Affordable Airpods Pro 2 \nStill Selling Fast \n\n₦60,000",
          "url": "https://www.instagram.com/reel/DI4VTgJsGY0",
          "statistics": {
            "likes": 42,
            "comments": 4,
            "views": 5090,
            "shares": 0
          }
        },
        "hashtags": [],
        "publishedTime": "2025-04-25T18:52:31.000Z",
        "platform": "Instagram",
        "postType": "Video",
        "mediaUrl": "https://scontent-lax3-2.cdninstagram.com/v/t51.75761-15/491235175_18502325368015148_6964612918238192395_n.jpg?stp=dst-jpg_e15_tt6&_nc_cat=103&ig_cache_key=MzYxODczNTk5OTc2MTI3ODUxNg%3D%3D.3-ccb1-7&ccb=1-7&_nc_sid=58cdad&efg=eyJ2ZW5jb2RlX3RhZyI6InhwaWRzLjcyMHgxMjgwLnNkciJ9&_nc_ohc=EjhBnZgTf1YQ7kNvwGAOEVB&_nc_oc=AdnIyHWfxIV5rn87Esk04xogq1BRXe67HWWTM9_NyrUQAKi_Q3OlMxVKKwBUWtYMGzU&_nc_ad=z-m&_nc_cid=0&_nc_zt=23&_nc_ht=scontent-lax3-2.cdninstagram.com&_nc_gid=K5AjRxJ13kAgLaWaMGC1bQ&oh=00_AfTPlBRpYVzeE_rzNgC0pyreSMUp8RzaNm5Ia98lfi9gkw&oe=68805F1D",
        "postId": "3618735999761278516_748687147",
        "shortCode": "DI4VTgJsGY0",
        "ownerUsername": "phonesvendor",
        "ownerFullName": "PHONE VENDOR - phones📱laptops 💻 games 🎮 accessories 🔌",
        "ownerId": 748687147,
        "enhancementStatus": "completed"
      },
      {
        "creator": {
          "name": "Niels | Apple & iPhone Expert",
          "uniqueId": "appledsign",
          "followers": 4832104,
          "avatarUrl": "https://scontent-lax3-2.cdninstagram.com/v/t51.2885-19/394467358_182729744877784_9135295416579514828_n.jpg?stp=dst-jpg_e0_s150x150_tt6&_nc_ht=scontent-lax3-2.cdninstagram.com&_nc_cat=1&_nc_oc=Q6cZ2QGOVUycnKDu-w2BPgYicYzZQI0oAb3CdkjydDw_CmlZzb_EhX9DMymbDteU5Kw93xs&_nc_ohc=7KNxQlKaUSIQ7kNvwF75Zpb&_nc_gid=K5AjRxJ13kAgLaWaMGC1bQ&edm=AL2I2h8BAAAA&ccb=7-5&oh=00_AfTO7jwIMPgQKz46pgqtvALYY_JWUE7ooZ0VDXcMeg_wZw&oe=6880432C&_nc_sid=026283",
          "profilePicUrl": "https://scontent-lax3-2.cdninstagram.com/v/t51.2885-19/394467358_182729744877784_9135295416579514828_n.jpg?stp=dst-jpg_e0_s150x150_tt6&_nc_ht=scontent-lax3-2.cdninstagram.com&_nc_cat=1&_nc_oc=Q6cZ2QGOVUycnKDu-w2BPgYicYzZQI0oAb3CdkjydDw_CmlZzb_EhX9DMymbDteU5Kw93xs&_nc_ohc=7KNxQlKaUSIQ7kNvwF75Zpb&_nc_gid=K5AjRxJ13kAgLaWaMGC1bQ&edm=AL2I2h8BAAAA&ccb=7-5&oh=00_AfTO7jwIMPgQKz46pgqtvALYY_JWUE7ooZ0VDXcMeg_wZw&oe=6880432C&_nc_sid=026283",
          "verified": true,
          "bio": "I teach you the best iPhone & Apple Tricks!\nYour #1 iPhone, MacBook, iPad & Apple Expert!\nBusiness: appledsign@gmail.com\nLinks you need to check:",
          "emails": [
            "appledsign@gmail.com"
          ],
          "qualityScore": 1075,
          "engagementRate": 0
        },
        "video": {
          "description": "8D + AirPods Pro/Max + ANC = Music Heaven!\n______\n#airpodsmax #8daudio #airpodspro #audioexperience #refinedsign",
          "url": "https://www.instagram.com/reel/C-VY17dtwoM",
          "statistics": {
            "likes": 1503418,
            "comments": 21256,
            "views": 44416171,
            "shares": 0
          }
        },
        "hashtags": [
          "#airpodsmax",
          "#8daudio",
          "#airpodspro",
          "#audioexperience",
          "#refinedsign"
        ],
        "publishedTime": "2024-08-06T15:56:00.000Z",
        "platform": "Instagram",
        "postType": "Video",
        "mediaUrl": "https://scontent-lax3-2.cdninstagram.com/v/t51.71878-15/504435265_736021589124471_4774182167607167764_n.jpg?stp=dst-jpg_e15_tt6&_nc_cat=106&ig_cache_key=MzQyODc1NTk1MDQxMDMzNjc4MA%3D%3D.3-ccb1-7&ccb=1-7&_nc_sid=58cdad&efg=eyJ2ZW5jb2RlX3RhZyI6InhwaWRzLjcyMHgxMjgwLnNkciJ9&_nc_ohc=sPvdGWy890gQ7kNvwGDJyd7&_nc_oc=AdmTOJaKjPnUw8V1dv8CZGHXneKju16dQruH7MAE8SA0uf6ZqcnuQQznQt6TrZSsQjk&_nc_ad=z-m&_nc_cid=0&_nc_zt=23&_nc_ht=scontent-lax3-2.cdninstagram.com&_nc_gid=K5AjRxJ13kAgLaWaMGC1bQ&oh=00_AfTrXpDGxb_Ta395WNiI4aUKtOhROqSQ9ClzPtNwvgCC7Q&oe=68803531",
        "postId": "3428755950410336780_2924603762",
        "shortCode": "C-VY17dtwoM",
        "ownerUsername": "appledsign",
        "ownerFullName": "Niels | Apple & iPhone Expert",
        "ownerId": 2924603762,
        "enhancementStatus": "completed"
      },
      {
        "creator": {
          "name": "Nabeel Nawab",
          "uniqueId": "nawabnabeel",
          "followers": 389715,
          "avatarUrl": "https://scontent-lax3-1.cdninstagram.com/v/t51.2885-19/353647267_512251674360725_7144588717540000485_n.jpg?stp=dst-jpg_e0_s150x150_tt6&_nc_ht=scontent-lax3-1.cdninstagram.com&_nc_cat=105&_nc_oc=Q6cZ2QGOVUycnKDu-w2BPgYicYzZQI0oAb3CdkjydDw_CmlZzb_EhX9DMymbDteU5Kw93xs&_nc_ohc=a_cQtT6e1C0Q7kNvwF35wD2&_nc_gid=K5AjRxJ13kAgLaWaMGC1bQ&edm=AL2I2h8BAAAA&ccb=7-5&oh=00_AfR_zddjfuxCyiRUhIDNvwMLc1Uzp13rarBSWpINo0VBEQ&oe=688063B8&_nc_sid=026283",
          "profilePicUrl": "https://scontent-lax3-1.cdninstagram.com/v/t51.2885-19/353647267_512251674360725_7144588717540000485_n.jpg?stp=dst-jpg_e0_s150x150_tt6&_nc_ht=scontent-lax3-1.cdninstagram.com&_nc_cat=105&_nc_oc=Q6cZ2QGOVUycnKDu-w2BPgYicYzZQI0oAb3CdkjydDw_CmlZzb_EhX9DMymbDteU5Kw93xs&_nc_ohc=a_cQtT6e1C0Q7kNvwF35wD2&_nc_gid=K5AjRxJ13kAgLaWaMGC1bQ&edm=AL2I2h8BAAAA&ccb=7-5&oh=00_AfR_zddjfuxCyiRUhIDNvwMLc1Uzp13rarBSWpINo0VBEQ&oe=688063B8&_nc_sid=026283",
          "verified": true,
          "bio": "Tech Reviewer | 2M+ on YouTube\nForbes Top 100 Digital Stars 2023-’24, 2024-’25\n📩Promotions: nawabnabeel@gmail.com\nRepped by @socialcurrent.in\nLinks⬇️",
          "emails": [
            "nawabnabeel@gmail.com"
          ],
          "qualityScore": 1075,
          "engagementRate": 0
        },
        "video": {
          "description": "How to Spot Fake AirPods Pro: Color, Pop-Up & Charging\nSpot the difference between the original and the fake AirPods Pro! Although the fake ones look just like the original, there are some subtle differences. Check out the colour of the case, the lightning port, and the wireless charging capabilities to make sure you’re getting the real deal.\n#airpodspro #authenticvsfake #originalvsreplica #appleairpodspro #airpodspro",
          "url": "https://www.instagram.com/reel/CouyLijMUlF",
          "statistics": {
            "likes": 61351,
            "comments": 588,
            "views": 3980759,
            "shares": 0
          }
        },
        "hashtags": [
          "#airpodspro",
          "#authenticvsfake",
          "#originalvsreplica",
          "#appleairpodspro",
          "#airpodspro"
        ],
        "publishedTime": "2023-02-16T17:06:28.000Z",
        "platform": "Instagram",
        "postType": "Video",
        "mediaUrl": "https://scontent-lax3-1.cdninstagram.com/v/t51.71878-15/498666405_1745359016059038_7458952963416608289_n.jpg?stp=dst-jpg_e15_tt6&_nc_cat=102&ig_cache_key=MzAzOTU4NzQ5Mzg1OTExNzM4MQ%3D%3D.3-ccb1-7&ccb=1-7&_nc_sid=58cdad&efg=eyJ2ZW5jb2RlX3RhZyI6InhwaWRzLjcyMHgxMjgwLnNkciJ9&_nc_ohc=rPLnRAq3IDAQ7kNvwELi1z5&_nc_oc=AdlscRz05E4wyXikZA0DiYI6Aj2nr-Tj9vCY4HRxkaymVYLCdGFODd3EAQymtQVtNQo&_nc_ad=z-m&_nc_cid=0&_nc_zt=23&_nc_ht=scontent-lax3-1.cdninstagram.com&_nc_gid=K5AjRxJ13kAgLaWaMGC1bQ&oh=00_AfQwl5QDUhy2skVkDurdYuKKnpx0P0nXDsYRpMrMEuk39w&oe=68806045",
        "postId": "3039587493859117381_2268352966",
        "shortCode": "CouyLijMUlF",
        "ownerUsername": "nawabnabeel",
        "ownerFullName": "Nabeel Nawab",
        "ownerId": 2268352966,
        "enhancementStatus": "completed"
      },
      {
        "creator": {
          "name": "Tyler",
          "uniqueId": "hitomidocameraroll",
          "followers": 508446,
          "avatarUrl": "https://scontent-lax3-2.cdninstagram.com/v/t51.2885-19/465052085_514392688093225_1091416479282304052_n.jpg?stp=dst-jpg_e0_s150x150_tt6&_nc_ht=scontent-lax3-2.cdninstagram.com&_nc_cat=1&_nc_oc=Q6cZ2QGOVUycnKDu-w2BPgYicYzZQI0oAb3CdkjydDw_CmlZzb_EhX9DMymbDteU5Kw93xs&_nc_ohc=EqEYwcon9pEQ7kNvwGjeOCD&_nc_gid=K5AjRxJ13kAgLaWaMGC1bQ&edm=AL2I2h8BAAAA&ccb=7-5&oh=00_AfTYm4kVQ6tcElZdVrFYHkGXFuHSkFxo0DnT1i1aEs56RA&oe=68804D30&_nc_sid=026283",
          "profilePicUrl": "https://scontent-lax3-2.cdninstagram.com/v/t51.2885-19/465052085_514392688093225_1091416479282304052_n.jpg?stp=dst-jpg_e0_s150x150_tt6&_nc_ht=scontent-lax3-2.cdninstagram.com&_nc_cat=1&_nc_oc=Q6cZ2QGOVUycnKDu-w2BPgYicYzZQI0oAb3CdkjydDw_CmlZzb_EhX9DMymbDteU5Kw93xs&_nc_ohc=EqEYwcon9pEQ7kNvwGjeOCD&_nc_gid=K5AjRxJ13kAgLaWaMGC1bQ&edm=AL2I2h8BAAAA&ccb=7-5&oh=00_AfTYm4kVQ6tcElZdVrFYHkGXFuHSkFxo0DnT1i1aEs56RA&oe=68804D30&_nc_sid=026283",
          "verified": true,
          "bio": "Don’t be a <^#+\n🇬🇧 +🇯🇵\n✉️ hitomidobusiness@gmail.com",
          "emails": [
            "hitomidobusiness@gmail.com"
          ],
          "qualityScore": 1075,
          "engagementRate": 0
        },
        "video": {
          "description": "Nothing Headphone (2) will 1000% be better than AirPods Max. Let’s be honest, Apple’s probably not releasing AirPods Pro 2 this year.\n#headphones #airpodsmax #nothingheadphone1",
          "url": "https://www.instagram.com/reel/DLosiuDOTYc",
          "statistics": {
            "likes": 13164,
            "comments": 109,
            "views": 368188,
            "shares": 0
          }
        },
        "hashtags": [
          "#headphones",
          "#airpodsmax",
          "#nothingheadphone1"
        ],
        "publishedTime": "2025-07-03T06:40:16.000Z",
        "platform": "Instagram",
        "postType": "Video",
        "mediaUrl": "https://scontent-lax3-1.cdninstagram.com/v/t51.82787-15/504731574_17963019728944809_1434963443364037322_n.jpg?stp=dst-jpg_e15_tt6&_nc_cat=110&ig_cache_key=MzY2ODM3Nzc5NjQ0ODE3MTU0OA%3D%3D.3-ccb1-7&ccb=1-7&_nc_sid=58cdad&efg=eyJ2ZW5jb2RlX3RhZyI6InhwaWRzLjcyMHgxMjgwLnNkciJ9&_nc_ohc=aSx0Up_rGpYQ7kNvwHtIIN8&_nc_oc=AdlxAQtZtm1JHpFKxJGDuA2DozR0N1XxHhiMvUWSeokp78Es7ywX6_84L4z8tvw2WQM&_nc_ad=z-m&_nc_cid=0&_nc_zt=23&_nc_ht=scontent-lax3-1.cdninstagram.com&_nc_gid=K5AjRxJ13kAgLaWaMGC1bQ&oh=00_AfRcczZV8_SQ5Hgi1cyucKw6MlkrTmTsGvUzbNTA-v0eCg&oe=68806411",
        "postId": "3668377796448171548_58432304808",
        "shortCode": "DLosiuDOTYc",
        "ownerUsername": "hitomidocameraroll",
        "ownerFullName": "Tyler",
        "ownerId": 58432304808,
        "enhancementStatus": "completed"
      },
      {
        "creator": {
          "name": "Hasan Karimi",
          "uniqueId": "hasankarimiofficial",
          "followers": 184752,
          "avatarUrl": "https://instagram.fsqx1-1.fna.fbcdn.net/v/t51.2885-19/464760996_1254146839119862_3605321457742435801_n.png?stp=dst-jpg_e0_s150x150_tt6&cb=8577c754-c2464923&_nc_ht=instagram.fsqx1-1.fna.fbcdn.net&_nc_cat=1&_nc_oc=Q6cZ2QFa8H53QLgVcqvMelp-dLpnGBrWQQv3V8U8aOzzcROLEmkKXNK-jwQXH4Lasm70eGQJ4IS2dxSrKFisn1qSlslV&_nc_ohc=DaCttfv6CKgQ7kNvwF0z4y2&_nc_gid=ciGHyIOkb4GTfADJIkDbGA&edm=AP7HCqgBAAAA&ccb=7-5&ig_cache_key=YW5vbnltb3VzX3Byb2ZpbGVfcGlj.3-ccb7-5-cb8577c754-c2464923&oh=00_AfRJF1jHpLc4uzha41khXH2j8gg-_KhRfsGR3xnvkUuSeQ&oe=68805168&_nc_sid=b09b61",
          "profilePicUrl": "https://instagram.fsqx1-1.fna.fbcdn.net/v/t51.2885-19/464760996_1254146839119862_3605321457742435801_n.png?stp=dst-jpg_e0_s150x150_tt6&cb=8577c754-c2464923&_nc_ht=instagram.fsqx1-1.fna.fbcdn.net&_nc_cat=1&_nc_oc=Q6cZ2QFa8H53QLgVcqvMelp-dLpnGBrWQQv3V8U8aOzzcROLEmkKXNK-jwQXH4Lasm70eGQJ4IS2dxSrKFisn1qSlslV&_nc_ohc=DaCttfv6CKgQ7kNvwF0z4y2&_nc_gid=ciGHyIOkb4GTfADJIkDbGA&edm=AP7HCqgBAAAA&ccb=7-5&ig_cache_key=YW5vbnltb3VzX3Byb2ZpbGVfcGlj.3-ccb7-5-cb8577c754-c2464923&oh=00_AfRJF1jHpLc4uzha41khXH2j8gg-_KhRfsGR3xnvkUuSeQ&oe=68805168&_nc_sid=b09b61",
          "verified": false,
          "bio": "همه چی در مورد رسانه های اجتماعی\nmosalah iranian ⚽️\nSocial media expert | Content Creator",
          "emails": [],
          "qualityScore": 75,
          "engagementRate": 0
        },
        "video": {
          "description": "🔥 AirPods Pro 2 — وقتی تکنولوژی، هنر می‌شه 🎧\n\nبا نسل جدید ایرپادز پرو،\nصدا فقط شنیده نمی‌شه، حس می‌شه.\n‌\n🎯 حذف نویز هوشمند\n🎧 صدای فضایی دقیقاً مطابق گوش تو\n🔋 تا ۶ ساعت شارژ بی‌وقفه\n‌\nدر مسیر، باشگاه، سفر یا حتی لحظه‌های سکوت...\nAirPods Pro 2 همیشه همراهته؛ بی‌وقفه، بی‌نقص، بی‌رقیب.\n\n📦 آماده تحویل | \n📩 برای سفارش دایرکت بده\n\n#AirPodsPro #اپل #ایرپادز۲ #تکنولوژی_هوشمند #گوشی_بی‌سیم #حذف_نویز #صدای_فضایی #اکسسوری_لوکس #دیجیتال_استایل #AppleGear",
          "url": "https://www.instagram.com/reel/DKP9KI7PlpC",
          "statistics": {
            "likes": 3,
            "comments": 67,
            "views": 73179,
            "shares": 0
          }
        },
        "hashtags": [
          "#AirPodsPro",
          "#AppleGear"
        ],
        "publishedTime": "2025-05-29T19:33:13.000Z",
        "platform": "Instagram",
        "postType": "Video",
        "mediaUrl": "https://scontent-lax3-1.cdninstagram.com/v/t51.71878-15/502707242_1704412320185345_1961769701648504936_n.jpg?stp=dst-jpg_e15_tt6&_nc_cat=104&ig_cache_key=MzY0MzM5OTYwMTE4MTg0MTk4Ng%3D%3D.3-ccb1-7&ccb=1-7&_nc_sid=58cdad&efg=eyJ2ZW5jb2RlX3RhZyI6InhwaWRzLjY0MHgxMTM2LnNkciJ9&_nc_ohc=jFsBLfAaKK8Q7kNvwFmEQKK&_nc_oc=AdkdyFSsuLQTDJLxMQilLuDSMSqCeTPjKXA-SO45k9y2wBkg3Iw6vwLBYR7RVCsHFpI&_nc_ad=z-m&_nc_cid=0&_nc_zt=23&_nc_ht=scontent-lax3-1.cdninstagram.com&_nc_gid=K5AjRxJ13kAgLaWaMGC1bQ&oh=00_AfSgic31ExcAPDZySOyFkLEO9bQdCyVGn33OZWTIlSOZBw&oe=68806321",
        "postId": "3643399601181841986_45001309995",
        "shortCode": "DKP9KI7PlpC",
        "ownerUsername": "hasankarimiofficial",
        "ownerFullName": "Hasan Karimi",
        "ownerId": 45001309995,
        "enhancementStatus": "completed"
      },
      {
        "creator": {
          "name": "Dark Tech",
          "uniqueId": "darktechofficial",
          "followers": 7844,
          "avatarUrl": "https://scontent-lax3-2.cdninstagram.com/v/t51.2885-19/461759910_519473034356051_7249716581705272233_n.jpg?stp=dst-jpg_e0_s150x150_tt6&_nc_ht=scontent-lax3-2.cdninstagram.com&_nc_cat=111&_nc_oc=Q6cZ2QGOVUycnKDu-w2BPgYicYzZQI0oAb3CdkjydDw_CmlZzb_EhX9DMymbDteU5Kw93xs&_nc_ohc=IeCMIoIEk-oQ7kNvwH6EY4j&_nc_gid=K5AjRxJ13kAgLaWaMGC1bQ&edm=AL2I2h8BAAAA&ccb=7-5&oh=00_AfRemGvDO-X3beKx7bIdkMySzziEWcvp4MtokUxOA_acZg&oe=68805DB7&_nc_sid=026283",
          "profilePicUrl": "https://scontent-lax3-2.cdninstagram.com/v/t51.2885-19/461759910_519473034356051_7249716581705272233_n.jpg?stp=dst-jpg_e0_s150x150_tt6&_nc_ht=scontent-lax3-2.cdninstagram.com&_nc_cat=111&_nc_oc=Q6cZ2QGOVUycnKDu-w2BPgYicYzZQI0oAb3CdkjydDw_CmlZzb_EhX9DMymbDteU5Kw93xs&_nc_ohc=IeCMIoIEk-oQ7kNvwH6EY4j&_nc_gid=K5AjRxJ13kAgLaWaMGC1bQ&edm=AL2I2h8BAAAA&ccb=7-5&oh=00_AfRemGvDO-X3beKx7bIdkMySzziEWcvp4MtokUxOA_acZg&oe=68805DB7&_nc_sid=026283",
          "verified": false,
          "bio": "Dark Tech is a leading provider of premium mobile accessories designed to elevate your tech experience.",
          "emails": [],
          "qualityScore": 75,
          "engagementRate": 0
        },
        "video": {
          "description": "AirPods Pro 2 \nImmersive sound, adaptive noise cancellation, and all-day comfort — the AirPods Pro 2 redefine wireless listening\n\n#AirPodsPro2 #Apple #WirelessEarbuds #NoiseCancellation #TechLifestyle #SoundWithoutLimits #AudioInnovation #AppleAccessories #NextGenAudio #ProSound #darktechofficial",
          "url": "https://www.instagram.com/reel/DJgji1mN2Mq",
          "statistics": {
            "likes": 15,
            "comments": 0,
            "views": 1989,
            "shares": 0
          }
        },
        "hashtags": [
          "#AirPodsPro2",
          "#Apple",
          "#WirelessEarbuds",
          "#NoiseCancellation",
          "#TechLifestyle",
          "#SoundWithoutLimits",
          "#AudioInnovation",
          "#AppleAccessories",
          "#NextGenAudio",
          "#ProSound",
          "#darktechofficial"
        ],
        "publishedTime": "2025-05-11T09:47:06.000Z",
        "platform": "Instagram",
        "postType": "Video",
        "mediaUrl": "https://scontent-lax3-2.cdninstagram.com/v/t51.75761-15/497044490_17878790301303095_9139729879234684223_n.jpg?stp=dst-jpg_e15_p750x750_tt6&_nc_cat=101&ig_cache_key=MzYzMDA1NzYyNTMwMDE5ODE4NjE3ODc4NzkwMjk1MzAzMDk1.3-ccb1-7&ccb=1-7&_nc_sid=58cdad&efg=eyJ2ZW5jb2RlX3RhZyI6InhwaWRzLjc2MHgxMzUwLnNkciJ9&_nc_ohc=T9rK1fXEq1oQ7kNvwG6hqzv&_nc_oc=AdmNe4YQb9uLoTNnJEMThRY4xzc7ykM5iReHv4H8y0gl67l_8_pZ7_OOZp7oWD6TMKQ&_nc_ad=z-m&_nc_cid=0&_nc_zt=23&_nc_ht=scontent-lax3-2.cdninstagram.com&_nc_gid=K5AjRxJ13kAgLaWaMGC1bQ&oh=00_AfQLqaJTGTjmhGWoC_SQH6uxSWduy6tBgQWQe06HSiivLQ&oe=68805A54",
        "postId": "3630057625300198186_69044671094",
        "shortCode": "DJgji1mN2Mq",
        "ownerUsername": "darktechofficial",
        "ownerFullName": "Dark Tech",
        "ownerId": 69044671094,
        "enhancementStatus": "completed"
      },
      {
        "creator": {
          "name": "E Case Tecnology",
          "uniqueId": "ecasetech",
          "followers": 17086,
          "avatarUrl": "https://scontent-lax3-1.cdninstagram.com/v/t51.2885-19/405206774_1046717423280856_686068739344952951_n.jpg?stp=dst-jpg_e0_s150x150_tt6&_nc_ht=scontent-lax3-1.cdninstagram.com&_nc_cat=104&_nc_oc=Q6cZ2QGOVUycnKDu-w2BPgYicYzZQI0oAb3CdkjydDw_CmlZzb_EhX9DMymbDteU5Kw93xs&_nc_ohc=t713uX5Xv8QQ7kNvwEC9rOW&_nc_gid=K5AjRxJ13kAgLaWaMGC1bQ&edm=AL2I2h8BAAAA&ccb=7-5&oh=00_AfRzeqe0jpiEO8_WPDBIrGHB4i-7_vSYfB5m5IRdE6es_g&oe=688061BE&_nc_sid=026283",
          "profilePicUrl": "https://scontent-lax3-1.cdninstagram.com/v/t51.2885-19/405206774_1046717423280856_686068739344952951_n.jpg?stp=dst-jpg_e0_s150x150_tt6&_nc_ht=scontent-lax3-1.cdninstagram.com&_nc_cat=104&_nc_oc=Q6cZ2QGOVUycnKDu-w2BPgYicYzZQI0oAb3CdkjydDw_CmlZzb_EhX9DMymbDteU5Kw93xs&_nc_ohc=t713uX5Xv8QQ7kNvwEC9rOW&_nc_gid=K5AjRxJ13kAgLaWaMGC1bQ&edm=AL2I2h8BAAAA&ccb=7-5&oh=00_AfRzeqe0jpiEO8_WPDBIrGHB4i-7_vSYfB5m5IRdE6es_g&oe=688061BE&_nc_sid=026283",
          "verified": false,
          "bio": "Referencia en Garantía de la Ciudad de Santiago🔰\nEst. 2012©️\nTelefonos\n-Accesorios \n-Servicio tecnico.",
          "emails": [],
          "qualityScore": 75,
          "engagementRate": 0
        },
        "video": {
          "description": "Disponible AirPods Pro 2 Generación 🔥 NEW NEW NEW!",
          "url": "https://www.instagram.com/reel/C_OKwVwOJUu",
          "statistics": {
            "likes": 243,
            "comments": 14,
            "views": 117201,
            "shares": 0
          }
        },
        "hashtags": [],
        "publishedTime": "2024-08-28T17:07:49.000Z",
        "platform": "Instagram",
        "postType": "Video",
        "mediaUrl": "https://scontent-lax3-1.cdninstagram.com/v/t51.71878-15/503753936_1636690697050565_5554682416000588326_n.jpg?stp=dst-jpg_e15_tt6&_nc_cat=104&ig_cache_key=MzQ0NDczODA2NzM0MjU5NTM3NA%3D%3D.3-ccb1-7&ccb=1-7&_nc_sid=58cdad&efg=eyJ2ZW5jb2RlX3RhZyI6InhwaWRzLjcyMHgxMjgwLnNkciJ9&_nc_ohc=1J5wcctoBF4Q7kNvwGEDrt3&_nc_oc=AdnJzZYfGFA1bRazgome_uNmKhfag9z5PxC8K9swrtjyHSnAd3mE5bbLnLD8DaXDuP0&_nc_ad=z-m&_nc_cid=0&_nc_zt=23&_nc_ht=scontent-lax3-1.cdninstagram.com&_nc_gid=K5AjRxJ13kAgLaWaMGC1bQ&oh=00_AfSVbaEZIfRlQX1eYlZRxi5V3OqzP2gyvKIOMUuzbnF2tw&oe=688032D0",
        "postId": "3444738067342595374_208966028",
        "shortCode": "C_OKwVwOJUu",
        "ownerUsername": "ecasetech",
        "ownerFullName": "E Case Tecnology",
        "ownerId": 208966028,
        "enhancementStatus": "completed"
      },
      {
        "creator": {
          "name": "Cases | Chargers | Screen Protector | Straps",
          "uniqueId": "titaniumcaseske",
          "followers": 8179,
          "avatarUrl": "https://scontent-lax3-1.cdninstagram.com/v/t51.2885-19/441306597_1085595002544557_4025321801521484720_n.jpg?stp=dst-jpg_e0_s150x150_tt6&_nc_ht=scontent-lax3-1.cdninstagram.com&_nc_cat=105&_nc_oc=Q6cZ2QGOVUycnKDu-w2BPgYicYzZQI0oAb3CdkjydDw_CmlZzb_EhX9DMymbDteU5Kw93xs&_nc_ohc=jMZpf5gW8v8Q7kNvwFHLU2w&_nc_gid=K5AjRxJ13kAgLaWaMGC1bQ&edm=AL2I2h8BAAAA&ccb=7-5&oh=00_AfRL46ombvaU40mDfP86XqnJ1P6-cMIvXuvxESqrfwxtqA&oe=688034CE&_nc_sid=026283",
          "profilePicUrl": "https://scontent-lax3-1.cdninstagram.com/v/t51.2885-19/441306597_1085595002544557_4025321801521484720_n.jpg?stp=dst-jpg_e0_s150x150_tt6&_nc_ht=scontent-lax3-1.cdninstagram.com&_nc_cat=105&_nc_oc=Q6cZ2QGOVUycnKDu-w2BPgYicYzZQI0oAb3CdkjydDw_CmlZzb_EhX9DMymbDteU5Kw93xs&_nc_ohc=jMZpf5gW8v8Q7kNvwFHLU2w&_nc_gid=K5AjRxJ13kAgLaWaMGC1bQ&edm=AL2I2h8BAAAA&ccb=7-5&oh=00_AfRL46ombvaU40mDfP86XqnJ1P6-cMIvXuvxESqrfwxtqA&oe=688034CE&_nc_sid=026283",
          "verified": false,
          "bio": "(Formerly known as ‘Titanium Cases’)\n✨In our phone accessories era\n📍Pioneer House Kimathi, Kimathi Street, 6th Floor, Office No.6",
          "emails": [],
          "qualityScore": 75,
          "engagementRate": 0
        },
        "video": {
          "description": "AirPods Pro Case -1000/=",
          "url": "https://www.instagram.com/reel/DB89cVxIDdQ",
          "statistics": {
            "likes": 73,
            "comments": 2,
            "views": 21271,
            "shares": 0
          }
        },
        "hashtags": [],
        "publishedTime": "2024-11-04T14:18:13.000Z",
        "platform": "Instagram",
        "postType": "Video",
        "mediaUrl": "https://scontent-lax3-2.cdninstagram.com/v/t51.71878-15/465879454_536478765829294_4844350047308778989_n.jpg?stp=dst-jpg_e15_tt6&_nc_cat=111&ig_cache_key=MzQ5MzkzNzYzOTI4Nzk2MTQyNA%3D%3D.3-ccb1-7&ccb=1-7&_nc_sid=58cdad&efg=eyJ2ZW5jb2RlX3RhZyI6InhwaWRzLjY0MHgxMTM2LnNkciJ9&_nc_ohc=DXHAzZne9vAQ7kNvwFiugjd&_nc_oc=Adlmq9JxnprzUKlLnf-SVb6mOxGZxf1_AjYuS_nzFIxg0ecsahQlyeOB3aDus91QCkU&_nc_ad=z-m&_nc_cid=0&_nc_zt=23&_nc_ht=scontent-lax3-2.cdninstagram.com&_nc_gid=K5AjRxJ13kAgLaWaMGC1bQ&oh=00_AfQnTXq7qIzjb7g7h6atPvHKNgnp6MMk8dyKSKHUDE5khg&oe=6880654F",
        "postId": "3493937639287961424_55335302119",
        "shortCode": "DB89cVxIDdQ",
        "ownerUsername": "titaniumcaseske",
        "ownerFullName": "Cases | Chargers | Screen Protector | Straps",
        "ownerId": 55335302119,
        "enhancementStatus": "completed"
      },
      {
        "creator": {
          "name": "АКСЕССУАРЫ/ ГАДЖЕТЫ/ НАУШНИКИ",
          "uniqueId": "easy_shop_new",
          "followers": 73337,
          "avatarUrl": "https://scontent-lax3-1.cdninstagram.com/v/t51.2885-19/290569580_1193150468149473_4039430368021182478_n.jpg?stp=dst-jpg_e0_s150x150_tt6&_nc_ht=scontent-lax3-1.cdninstagram.com&_nc_cat=109&_nc_oc=Q6cZ2QGOVUycnKDu-w2BPgYicYzZQI0oAb3CdkjydDw_CmlZzb_EhX9DMymbDteU5Kw93xs&_nc_ohc=6dmMm-x_zxkQ7kNvwEYr0B-&_nc_gid=K5AjRxJ13kAgLaWaMGC1bQ&edm=AL2I2h8BAAAA&ccb=7-5&oh=00_AfSbSo4EIfuOz3W7gtHgaSo2ulefvfOgAJFt7m7NqVt1Gw&oe=6880475A&_nc_sid=026283",
          "profilePicUrl": "https://scontent-lax3-1.cdninstagram.com/v/t51.2885-19/290569580_1193150468149473_4039430368021182478_n.jpg?stp=dst-jpg_e0_s150x150_tt6&_nc_ht=scontent-lax3-1.cdninstagram.com&_nc_cat=109&_nc_oc=Q6cZ2QGOVUycnKDu-w2BPgYicYzZQI0oAb3CdkjydDw_CmlZzb_EhX9DMymbDteU5Kw93xs&_nc_ohc=6dmMm-x_zxkQ7kNvwEYr0B-&_nc_gid=K5AjRxJ13kAgLaWaMGC1bQ&edm=AL2I2h8BAAAA&ccb=7-5&oh=00_AfSbSo4EIfuOz3W7gtHgaSo2ulefvfOgAJFt7m7NqVt1Gw&oe=6880475A&_nc_sid=026283",
          "verified": false,
          "bio": "🔥Smart Watch⌚️все виды AirPods 😍\n📍ТЦ \"EURASIA\" (Советская/Киевская) 1 - этаж\n🚀Доставка по всему Кыргызстану🇰🇬 \n💌Для заказа напишите сюда👇",
          "emails": [],
          "qualityScore": 75,
          "engagementRate": 0
        },
        "video": {
          "description": "Все виды AirPods \nВ подарок 🎁 чехол для наушников 🤗\n\nAirPods 2 (lux) - 👉1200 сом👈\nAirPods Pro (lux) - 👉1350 сом👈\nAirPods 3 (lux) - 👉1350сом👈\nAirPods Pro 2 (Lux) - 👉1500👈 с активным шумоподавлением ANC ✅\n\nФункционал AirPods почти одинаковый ⬇️\nОсновные характеристики:\n▪️Высокое качество звучания музыки и голоса✅\n▪️Автоматическое включение и подключение к устройству✅\n▪️Простая настройка для работы с любыми устройствами ✅\n▪️Двойное касание для начала воспроизведения или переключения на следующий трек✅\n▪️Быстрая подзарядка в футляре\n▪️Футляр заряжается через разъём Lightning✅\n▪️Воспроизведение музыки 3-4 часа✅\n\n📍Наш адрес: ТЦ «EURASIA» Абдрахманова/Киевская\n1 - этаж 🤗 100 - бутик \nГрафик работы: с 10:00 до 21:00 🕘 \n\nДля заказа пишите в Директ 📩\nили звоните 👇\n☎️ 0772868085 📞\n📩WhatsApp - 0772868085\n\nБезналичный расчёт: Элсом, Balance.kg, МБанк, Visa \n\n🚗 Доставка по всему Кыргызстану🇰🇬",
          "url": "https://www.instagram.com/reel/C9_yvWdosJ5",
          "statistics": {
            "likes": 2069,
            "comments": 47,
            "views": 1025471,
            "shares": 0
          }
        },
        "hashtags": [],
        "publishedTime": "2024-07-29T06:38:24.000Z",
        "platform": "Instagram",
        "postType": "Video",
        "mediaUrl": "https://scontent-lax3-2.cdninstagram.com/v/t51.71878-15/504328884_1057116503235476_8251635933020046843_n.jpg?stp=dst-jpg_e35_p750x750_sh0.08_tt6&_nc_cat=107&ig_cache_key=MzQyMjY3NzM5ODA4NTM1NDEwNQ%3D%3D.3-ccb1-7&ccb=1-7&_nc_sid=58cdad&efg=eyJ2ZW5jb2RlX3RhZyI6InhwaWRzLjIyNjh4NDAzMi5zZHIifQ%3D%3D&_nc_ohc=hTTNi7CdAe4Q7kNvwHHXlB7&_nc_oc=Adl9NITXi4kCh89wacdK1XW3sq0tPfgWK96KAu2FehUNytKHs-1QDdwEyLEoJh3jHcE&_nc_ad=z-m&_nc_cid=0&_nc_zt=23&_nc_ht=scontent-lax3-2.cdninstagram.com&_nc_gid=K5AjRxJ13kAgLaWaMGC1bQ&oh=00_AfThfgWCVt2IrzwAqh2kxxVdZzOQcP9NMSHV5jsxJs1wYg&oe=68806309",
        "postId": "3422677398085354105_54270322072",
        "shortCode": "C9_yvWdosJ5",
        "ownerUsername": "easy_shop_new",
        "ownerFullName": "АКСЕССУАРЫ/ ГАДЖЕТЫ/ НАУШНИКИ",
        "ownerId": 54270322072,
        "enhancementStatus": "completed"
      },
      {
        "creator": {
          "name": "𝐑𝐄𝐃 𝐌𝐎𝐁𝐈𝐋𝐄",
          "uniqueId": "red_mobile_tashkent",
          "followers": 29334,
          "avatarUrl": "https://scontent-lax3-1.cdninstagram.com/v/t51.2885-19/395118240_288128474176289_3700556946114359872_n.jpg?stp=dst-jpg_e0_s150x150_tt6&_nc_ht=scontent-lax3-1.cdninstagram.com&_nc_cat=105&_nc_oc=Q6cZ2QGOVUycnKDu-w2BPgYicYzZQI0oAb3CdkjydDw_CmlZzb_EhX9DMymbDteU5Kw93xs&_nc_ohc=Htpzd598RI4Q7kNvwFPWBVB&_nc_gid=K5AjRxJ13kAgLaWaMGC1bQ&edm=AL2I2h8BAAAA&ccb=7-5&oh=00_AfSvKbS4UjviMRT0rlyMU5jSfyeJ4GiEuCSYDGmpQ2KN6g&oe=68804F3F&_nc_sid=026283",
          "profilePicUrl": "https://scontent-lax3-1.cdninstagram.com/v/t51.2885-19/395118240_288128474176289_3700556946114359872_n.jpg?stp=dst-jpg_e0_s150x150_tt6&_nc_ht=scontent-lax3-1.cdninstagram.com&_nc_cat=105&_nc_oc=Q6cZ2QGOVUycnKDu-w2BPgYicYzZQI0oAb3CdkjydDw_CmlZzb_EhX9DMymbDteU5Kw93xs&_nc_ohc=Htpzd598RI4Q7kNvwFPWBVB&_nc_gid=K5AjRxJ13kAgLaWaMGC1bQ&edm=AL2I2h8BAAAA&ccb=7-5&oh=00_AfSvKbS4UjviMRT0rlyMU5jSfyeJ4GiEuCSYDGmpQ2KN6g&oe=68804F3F&_nc_sid=026283",
          "verified": false,
          "bio": "☎️ ● +𝟗𝟗𝟖 (𝟑𝟑) 𝟎𝟎𝟓 𝟑𝟎𝟑𝟎\n⚜️ ● 𝐍𝐚𝐪𝐝 𝐯𝐚 𝐍𝐚𝐬𝐢𝐲𝐚 𝐬𝐚𝐯𝐝𝐨 \n⚜️ ● 𝐓𝐫𝐚𝐝𝐞 𝐢𝐧\n⚜️ ● 𝐘𝐞𝐭𝐤𝐚𝐳𝐢𝐛 𝐛𝐞𝐫𝐢𝐬𝐡 𝐱𝐢𝐳𝐦𝐚𝐭𝐢\n🔽 🔽 🔽 • 𝐓𝐞𝐥𝐞𝐠𝐫𝐚𝐦 𝐤𝐚𝐧𝐚𝐥 • 🔽 🔽 🔽",
          "emails": [],
          "qualityScore": 75,
          "engagementRate": 0
        },
        "video": {
          "description": "🔈\nAirPods 2.1 \nAirPods Pro 2 \nAirPods Pro 2 2023 Tyb-c \nAirPods 3 \nAirPods Max \nEarPods Tyb-c\nEarPods Lighting",
          "url": "https://www.instagram.com/reel/C8CgrKhITkb",
          "statistics": {
            "likes": 38131,
            "comments": 2321,
            "views": 2368622,
            "shares": 0
          }
        },
        "hashtags": [],
        "publishedTime": "2024-06-10T14:55:22.000Z",
        "platform": "Instagram",
        "postType": "Video",
        "mediaUrl": "https://scontent-lax3-1.cdninstagram.com/v/t51.71878-15/502463194_1243967687223036_3151597497482731464_n.jpg?stp=dst-jpg_e15_tt6&_nc_cat=104&ig_cache_key=MzM4NzQxMzU3MzQ1NTEzMjk1NQ%3D%3D.3-ccb1-7&ccb=1-7&_nc_sid=58cdad&efg=eyJ2ZW5jb2RlX3RhZyI6InhwaWRzLjcyMHgxMjgwLnNkciJ9&_nc_ohc=jr_dfVXhkBwQ7kNvwGwc44E&_nc_oc=Adkh70zHIHA43KvBQNy7EftZ9lKoKyvqpIzbMkTUonRzuvcpUUAjQtSyGsZH6EXKilA&_nc_ad=z-m&_nc_cid=0&_nc_zt=23&_nc_ht=scontent-lax3-1.cdninstagram.com&_nc_gid=K5AjRxJ13kAgLaWaMGC1bQ&oh=00_AfQ8sNiPK3OFlyuy-Hdn-WwCMBCTDVCfZnfgNfndk-2mtQ&oe=68805ECF",
        "postId": "3387413573455132955_62260265528",
        "shortCode": "C8CgrKhITkb",
        "ownerUsername": "red_mobile_tashkent",
        "ownerFullName": "𝐑𝐄𝐃 𝐌𝐎𝐁𝐈𝐋𝐄",
        "ownerId": 62260265528,
        "enhancementStatus": "completed"
      },
      {
        "creator": {
          "name": "کیس موبایل  / قاب موبایل 📱",
          "uniqueId": "case__mobilee",
          "followers": 363689,
          "avatarUrl": "https://scontent-lax3-2.cdninstagram.com/v/t51.2885-19/307701678_786181886049851_9118887988082481265_n.jpg?stp=dst-jpg_e0_s150x150_tt6&_nc_ht=scontent-lax3-2.cdninstagram.com&_nc_cat=1&_nc_oc=Q6cZ2QGOVUycnKDu-w2BPgYicYzZQI0oAb3CdkjydDw_CmlZzb_EhX9DMymbDteU5Kw93xs&_nc_ohc=luI6wfLqEbUQ7kNvwGuqp6O&_nc_gid=K5AjRxJ13kAgLaWaMGC1bQ&edm=AL2I2h8BAAAA&ccb=7-5&oh=00_AfRthW1tf2tlO9X6DmVIvZdk1_H8OFZHQLynOyZNbM7MfA&oe=6880602C&_nc_sid=026283",
          "profilePicUrl": "https://scontent-lax3-2.cdninstagram.com/v/t51.2885-19/307701678_786181886049851_9118887988082481265_n.jpg?stp=dst-jpg_e0_s150x150_tt6&_nc_ht=scontent-lax3-2.cdninstagram.com&_nc_cat=1&_nc_oc=Q6cZ2QGOVUycnKDu-w2BPgYicYzZQI0oAb3CdkjydDw_CmlZzb_EhX9DMymbDteU5Kw93xs&_nc_ohc=luI6wfLqEbUQ7kNvwGuqp6O&_nc_gid=K5AjRxJ13kAgLaWaMGC1bQ&edm=AL2I2h8BAAAA&ccb=7-5&oh=00_AfRthW1tf2tlO9X6DmVIvZdk1_H8OFZHQLynOyZNbM7MfA&oe=6880602C&_nc_sid=026283",
          "verified": false,
          "bio": "انواع قاب و تجهيزات موبايل  📱\nارسال به تمام نقاط ايران ✈️\nجهت سفارش به دايركت مراجعه فرماييد 📥\nپیج اکسسوری : @case__mobilee_acc",
          "emails": [],
          "qualityScore": 75,
          "engagementRate": 0
        },
        "video": {
          "description": "قاب گوشی ابری هلوگرامی ☁️✨🌤️\nسامسونگ - آیفون - شیائومی\nدارای ست ایرپاد\nمتریال IMD \nپوشش کامل\nکیفیت عالی\nقیمت قاب : 420 هزار تومان\nقیمت ایرپاد : 420 هزار تومان \nموجود برای :\n.\niPhone :\n📱iPhone 16Promax\n📱iPhone 16Pro\n📱iPhone 16\n📱iPhone 15Promax\n📱iPhone 14Promax  \n📱iPhone 13Promax \n📱iPhone 13Pro \n📱iPhone 13/14\n📱iPhone 12Promax \n\nAirpods :\n🎧Airpods Pro/Pro2\n🎧Airpods 4\n🎧Airpods 3\n🎧Airpods 1/2\n\nSamsung Galaxy:\n🌌S25 Ultra\n🌌S24 Ultra\n🌌S23 Ultra\n🌌S24 FE\n🌌S23 FE\n🌌S21 FE\n🌌A73\n🌌A56\n🌌A55\n🌌A54\n🌌A53\n🌌A52/A52S\n🌌A35\n🌌A32 5G\n🌌A32 4G\n🌌A25\n🌌A16\n🌌A15\n🌌A13/A23/A04s\n\nMI:\n🔥Redmi Note 13Pro 4G/M6Pro\n🔥Redmi Note 13 4G\n🔥Redmi Note 11Pro/12pro 4G\n🔥Note 12pro 5G/Poco X5 Pro\n🔥Poco X3/X3Pro/ X3nfc\n.\nارسال به سراسر ایران\nجهت سفارش به دایرکت مراجعه فرمایید 🙏🏻⛈️",
          "url": "https://www.instagram.com/reel/DMIkIBQNc7k",
          "statistics": {
            "likes": 2712,
            "comments": 33,
            "views": 79338,
            "shares": 0
          }
        },
        "hashtags": [],
        "publishedTime": "2025-07-15T15:44:09.000Z",
        "platform": "Instagram",
        "postType": "Video",
        "mediaUrl": "https://scontent-lax3-1.cdninstagram.com/v/t51.71878-15/519621085_2802738266590955_705080623785072367_n.jpg?stp=dst-jpg_e15_tt6&_nc_cat=109&ig_cache_key=MzY3NzM0Nzk3NjUyMzkyNzI2OA%3D%3D.3-ccb1-7&ccb=1-7&_nc_sid=58cdad&efg=eyJ2ZW5jb2RlX3RhZyI6InhwaWRzLjY0MHgxMTM2LnNkciJ9&_nc_ohc=5JlQq5OzO8IQ7kNvwEfPpsh&_nc_oc=Adlz31HQk-9yn-xEq7rIUEQzwxM3MojX1-z7w-c0Ho_8mlxSW5uIXOWLHq-x8Js6Wxc&_nc_ad=z-m&_nc_cid=0&_nc_zt=23&_nc_ht=scontent-lax3-1.cdninstagram.com&_nc_gid=K5AjRxJ13kAgLaWaMGC1bQ&oh=00_AfSypjgv1v7h2Twt683q1pHoTdapEiqjtZrIlo4g6-gk5g&oe=68803B78",
        "postId": "3677347976523927268_576626489",
        "shortCode": "DMIkIBQNc7k",
        "ownerUsername": "case__mobilee",
        "ownerFullName": "کیس موبایل  / قاب موبایل 📱",
        "ownerId": 576626489,
        "enhancementStatus": "completed"
      }
    ]
  }
}