{
  "timestamp": "2025-07-20T13:19:08.954Z",
  "platform": "TikTok",
  "apiType": "Profile",
  "handle": "barstoolracing",
  "requestUrl": "https://api.scrapecreators.com/v1/tiktok/profile?handle=barstoolracing",
  "responseStatus": 200,
  "responseTime": 1994,
  "rawResponse": "{\"user\":{\"id\":\"7197109081160746030\",\"shortId\":\"\",\"uniqueId\":\"barstoolracing\",\"nickname\":\"Rubbin’ is Racing\",\"avatarLarger\":\"https://p19-pu-sign-useast8.tiktokcdn-us.com/tos-useast5-avt-0068-tx/7333463807978635307~tplv-tiktokx-cropcenter:1080:1080.jpeg?dr=9640&refresh_token=3a9853e1&x-expires=1753189200&x-signature=Lc100jkjQxrWYlHBKMM9Lc4iGzA%3D&t=4d5b0474&ps=13740610&shp=a5d48078&shcp=81f88b70&idc=useast5\",\"avatarMedium\":\"https://p16-pu-sign-useast8.tiktokcdn-us.com/tos-useast5-avt-0068-tx/7333463807978635307~tplv-tiktokx-cropcenter:720:720.jpeg?dr=9640&refresh_token=b6bd8740&x-expires=1753189200&x-signature=Jw38hSgRAyXiGRn3jUFbQnBpZYg%3D&t=4d5b0474&ps=13740610&shp=a5d48078&shcp=f20df69d&idc=useast5\",\"avatarThumb\":\"https://p19-pu-sign-useast8.tiktokcdn-us.com/tos-useast5-avt-0068-tx/7333463807978635307~tplv-tiktokx-cropcenter:100:100.jpeg?dr=9640&refresh_token=5c9e8bc1&x-expires=1753189200&x-signature=Avo7mCfa1KiKDXF6RKp5m5yloiE%3D&t=4d5b0474&ps=13740610&shp=a5d48078&shcp=f20df69d&idc=useast5\",\"signature\":\"@BarstoolSports NASCAR Coverage Hosted by Large & Spider!\",\"createTime\":1675707666,\"verified\":false,\"secUid\":\"MS4wLjABAAAAgj3xt9XBqFlZXZS6I1no9HQEULclzW_ZDDKjBO21Lwawqah-hNoBx6CnVKD2arv1\",\"ftc\":false,\"relation\":0,\"openFavorite\":false,\"bioLink\":{\"link\":\"https://linktr.ee/Rubbin_is_Racing\",\"risk\":0},\"commentSetting\":0,\"commerceUserInfo\":{\"commerceUser\":false},\"duetSetting\":0,\"stitchSetting\":0,\"privateAccount\":false,\"secret\":false,\"isADVirtual\":false,\"roomId\":\"\",\"uniqueIdModifyTime\":0,\"ttSeller\":false,\"downloadSetting\":0,\"profileTab\":{\"showMusicTab\":false,\"showQuestionTab\":false,\"showPlayListTab\":false},\"followingVisibility\":1,\"recommendReason\":\"\",\"nowInvitationCardUrl\":\"\",\"nickNameModifyTime\":1675707682,\"isEmbedBanned\":false,\"canExpPlaylist\":true,\"profileEmbedPermission\":1,\"language\":\"en\",\"eventList\":[],\"suggestAccountBind\":false,\"isOrganization\":0,\"UserStoryStatus\":0},\"stats\":{\"followerCount\":32100,\"followingCount\":7,\"heart\":109100,\"heartCount\":109100,\"videoCount\":99,\"diggCount\":0,\"friendCount\":5},\"statsV2\":{\"followerCount\":\"32109\",\"followingCount\":\"7\",\"heart\":\"109055\",\"heartCount\":\"109055\",\"videoCount\":\"99\",\"diggCount\":\"0\",\"friendCount\":\"5\"},\"itemList\":[]}"
}