{
  "timestamp": "2025-07-12T12:21:14.667Z",
  "platform": "TikTok",
  "apiType": "Profile",
  "handle": "portnoy7",
  "requestUrl": "https://api.scrapecreators.com/v1/tiktok/profile?handle=portnoy7",
  "responseStatus": 200,
  "responseTime": 2403,
  "rawResponse": "{\"user\":{\"id\":\"7317651782380766213\",\"shortId\":\"\",\"uniqueId\":\"portnoy7\",\"nickname\":\"portnoy\",\"avatarLarger\":\"https://p16-common-sign-va.tiktokcdn-us.com/tos-maliva-avt-0068/cdc02b930dbf55e213fb3d1e9bcb8bbf~tplv-tiktokx-cropcenter:1080:1080.jpeg?dr=9640&refresh_token=a584f36a&x-expires=1752494400&x-signature=o5tXmOEsMyGgn%2BMZ%2Bqw5dFyBAhg%3D&t=4d5b0474&ps=13740610&shp=a5d48078&shcp=81f88b70&idc=useast8\",\"avatarMedium\":\"https://p16-common-sign-va.tiktokcdn-us.com/tos-maliva-avt-0068/cdc02b930dbf55e213fb3d1e9bcb8bbf~tplv-tiktokx-cropcenter:720:720.jpeg?dr=9640&refresh_token=1281c067&x-expires=1752494400&x-signature=MXK4haFq58ToqBaljIo3u8viip8%3D&t=4d5b0474&ps=13740610&shp=a5d48078&shcp=81f88b70&idc=useast8\",\"avatarThumb\":\"https://p19-common-sign-va.tiktokcdn-us.com/tos-maliva-avt-0068/cdc02b930dbf55e213fb3d1e9bcb8bbf~tplv-tiktokx-cropcenter:100:100.jpeg?dr=9640&refresh_token=3d63a94f&x-expires=1752494400&x-signature=oRLc2AN5e3sDFCIE7Wme6wgqQsY%3D&t=4d5b0474&ps=13740610&shp=a5d48078&shcp=81f88b70&idc=useast8\",\"signature\":\"\",\"createTime\":1728704699,\"verified\":false,\"secUid\":\"MS4wLjABAAAAf4uGEbjNtsNcDbtcnHTNZ4SiWBbheHd5PaUfeWSXs5FQdrdjxZqq5IAVRCCCNcB6\",\"ftc\":false,\"relation\":0,\"openFavorite\":false,\"commentSetting\":0,\"commerceUserInfo\":{\"commerceUser\":false},\"duetSetting\":0,\"stitchSetting\":0,\"privateAccount\":false,\"secret\":false,\"isADVirtual\":false,\"roomId\":\"\",\"uniqueIdModifyTime\":0,\"ttSeller\":false,\"region\":\"ID\",\"downloadSetting\":0,\"profileTab\":{\"showMusicTab\":false,\"showQuestionTab\":false,\"showPlayListTab\":false},\"followingVisibility\":1,\"recommendReason\":\"\",\"nowInvitationCardUrl\":\"\",\"nickNameModifyTime\":1728704740,\"isEmbedBanned\":false,\"canExpPlaylist\":true,\"profileEmbedPermission\":1,\"language\":\"id\",\"eventList\":[],\"suggestAccountBind\":false,\"isOrganization\":0,\"UserStoryStatus\":0},\"stats\":{\"followerCount\":22,\"followingCount\":15,\"heart\":27,\"heartCount\":27,\"videoCount\":7,\"diggCount\":0,\"friendCount\":2},\"statsV2\":{\"followerCount\":\"22\",\"followingCount\":\"15\",\"heart\":\"27\",\"heartCount\":\"27\",\"videoCount\":\"7\",\"diggCount\":\"0\",\"friendCount\":\"2\"},\"itemList\":[]}"
}