{
  "timestamp": "2025-07-20T13:17:48.606Z",
  "platform": "TikTok",
  "apiType": "Profile",
  "handle": "daveb1013",
  "requestUrl": "https://api.scrapecreators.com/v1/tiktok/profile?handle=daveb1013",
  "responseStatus": 200,
  "responseTime": 2843,
  "rawResponse": "{\"user\":{\"id\":\"6974513761102431238\",\"shortId\":\"\",\"uniqueId\":\"daveb1013\",\"nickname\":\"DAVEB1013\",\"avatarLarger\":\"https://p16-pu-sign-useast8.tiktokcdn-us.com/tos-useast8-avt-0068-tx2/255da40936f585817069a5ccd0b3ad05~tplv-tiktokx-cropcenter:1080:1080.jpeg?dr=9640&refresh_token=96ab3035&x-expires=1753189200&x-signature=Gp2nWQg%2F8WFdLmPFvL1noasgtks%3D&t=4d5b0474&ps=13740610&shp=a5d48078&shcp=81f88b70&idc=useast8\",\"avatarMedium\":\"https://p16-pu-sign-useast8.tiktokcdn-us.com/tos-useast8-avt-0068-tx2/255da40936f585817069a5ccd0b3ad05~tplv-tiktokx-cropcenter:720:720.jpeg?dr=9640&refresh_token=c7c60365&x-expires=1753189200&x-signature=oQdI10wNdo8LcBXVb5%2FchByK5fE%3D&t=4d5b0474&ps=13740610&shp=a5d48078&shcp=81f88b70&idc=useast8\",\"avatarThumb\":\"https://p16-pu-sign-useast8.tiktokcdn-us.com/tos-useast8-avt-0068-tx2/255da40936f585817069a5ccd0b3ad05~tplv-tiktokx-cropcenter:100:100.jpeg?dr=9640&refresh_token=97f070b2&x-expires=1753189200&x-signature=WBwN1adJRgCTG400uzbiOmkikPY%3D&t=4d5b0474&ps=13740610&shp=a5d48078&shcp=81f88b70&idc=useast8\",\"signature\":\"Dad Gamer/Content Creator/\\nTech Jesus/Stream Guru\\nLive M, T, W, F 7pm EST\\n🔻🔻🔻\",\"createTime\":1623880826,\"verified\":false,\"secUid\":\"MS4wLjABAAAAPJb9doGXIs7k6GzHQ7rEtSFH-_bRWtSgPu1pPoJteRsqAEm_bqLUl32XTy0TtU0Z\",\"ftc\":false,\"relation\":0,\"openFavorite\":false,\"bioLink\":{\"link\":\"https://linktr.ee/daveb1013\",\"risk\":0},\"commentSetting\":0,\"commerceUserInfo\":{\"commerceUser\":false},\"duetSetting\":0,\"stitchSetting\":0,\"privateAccount\":false,\"secret\":false,\"isADVirtual\":false,\"roomId\":\"7529140677678992141\",\"uniqueIdModifyTime\":0,\"ttSeller\":false,\"downloadSetting\":0,\"profileTab\":{\"showMusicTab\":false,\"showQuestionTab\":true,\"showPlayListTab\":true},\"followingVisibility\":2,\"recommendReason\":\"\",\"nowInvitationCardUrl\":\"\",\"nickNameModifyTime\":1668457645,\"isEmbedBanned\":false,\"canExpPlaylist\":true,\"profileEmbedPermission\":1,\"language\":\"en\",\"eventList\":[],\"suggestAccountBind\":false,\"isOrganization\":0,\"UserStoryStatus\":0},\"stats\":{\"followerCount\":24300,\"followingCount\":2751,\"heart\":37200,\"heartCount\":37200,\"videoCount\":411,\"diggCount\":0,\"friendCount\":2346},\"statsV2\":{\"followerCount\":\"24346\",\"followingCount\":\"2751\",\"heart\":\"37180\",\"heartCount\":\"37180\",\"videoCount\":\"411\",\"diggCount\":\"0\",\"friendCount\":\"2346\"},\"itemList\":[]}"
}