{
  "timestamp": "2025-07-12T12:46:37.634Z",
  "platform": "TikTok",
  "apiType": "Profile",
  "handle": "chana.portnoy",
  "requestUrl": "https://api.scrapecreators.com/v1/tiktok/profile?handle=chana.portnoy",
  "responseStatus": 200,
  "responseTime": 1465,
  "rawResponse": "{\"user\":{\"id\":\"6701963702822175749\",\"shortId\":\"\",\"uniqueId\":\"chana.portnoy\",\"nickname\":\"Chana Portnoy\",\"avatarLarger\":\"https://p16-pu-sign-useast8.tiktokcdn-us.com/tos-useast8-avt-0068-tx2/aed6a56c58372eda16ea0e72452bd01e~tplv-tiktokx-cropcenter:1080:1080.jpeg?dr=9640&refresh_token=2f7de671&x-expires=1752494400&x-signature=N3sYfLLvirXHf1Y6IT9XUYmDZPI%3D&t=4d5b0474&ps=13740610&shp=a5d48078&shcp=81f88b70&idc=useast8\",\"avatarMedium\":\"https://p19-pu-sign-useast8.tiktokcdn-us.com/tos-useast8-avt-0068-tx2/aed6a56c58372eda16ea0e72452bd01e~tplv-tiktokx-cropcenter:720:720.jpeg?dr=9640&refresh_token=970ec07e&x-expires=1752494400&x-signature=F2K8nDhKmdIAcuggrpgTUQ%2F%2FDPk%3D&t=4d5b0474&ps=13740610&shp=a5d48078&shcp=81f88b70&idc=useast8\",\"avatarThumb\":\"https://p19-pu-sign-useast8.tiktokcdn-us.com/tos-useast8-avt-0068-tx2/aed6a56c58372eda16ea0e72452bd01e~tplv-tiktokx-cropcenter:100:100.jpeg?dr=9640&refresh_token=7ed15ed8&x-expires=1752494400&x-signature=vXEYER5sP9heBXj03VQydr4ph8o%3D&t=4d5b0474&ps=13740610&shp=a5d48078&shcp=81f88b70&idc=useast8\",\"signature\":\"\",\"createTime\":1560422603,\"verified\":false,\"secUid\":\"MS4wLjABAAAAyTlSj9nkcVkbLHgxwxXffmSIGnUctUkPkvtrSLPyxu4o1w8eg7nRObyJxDddTVfs\",\"ftc\":false,\"relation\":0,\"openFavorite\":false,\"commerceUserInfo\":{\"commerceUser\":false},\"privateAccount\":true,\"secret\":true,\"isADVirtual\":false,\"roomId\":\"\",\"uniqueIdModifyTime\":0,\"ttSeller\":false,\"region\":\"IL\",\"downloadSetting\":3,\"profileTab\":{\"showMusicTab\":false,\"showQuestionTab\":false,\"showPlayListTab\":false},\"followingVisibility\":1,\"recommendReason\":\"\",\"nowInvitationCardUrl\":\"\",\"nickNameModifyTime\":1610927278,\"isEmbedBanned\":false,\"canExpPlaylist\":true,\"profileEmbedPermission\":3,\"language\":\"en\",\"suggestAccountBind\":false,\"isOrganization\":0,\"UserStoryStatus\":0},\"stats\":{\"followerCount\":381,\"followingCount\":352,\"heart\":14000,\"heartCount\":14000,\"videoCount\":0,\"diggCount\":0,\"friendCount\":232},\"statsV2\":{\"followerCount\":\"381\",\"followingCount\":\"352\",\"heart\":\"13973\",\"heartCount\":\"13973\",\"videoCount\":\"0\",\"diggCount\":\"0\",\"friendCount\":\"232\"},\"itemList\":[]}"
}