{
  "timestamp": "2025-07-20T13:18:40.015Z",
  "platform": "TikTok",
  "apiType": "Profile",
  "handle": "fitdadceo",
  "requestUrl": "https://api.scrapecreators.com/v1/tiktok/profile?handle=fitdadceo",
  "responseStatus": 200,
  "responseTime": 1466,
  "rawResponse": "{\"user\":{\"id\":\"268697694620217344\",\"shortId\":\"\",\"uniqueId\":\"fitdadceo\",\"nickname\":\"Dave FitDad Ogleton\",\"avatarLarger\":\"https://p16-common-sign-va.tiktokcdn-us.com/tos-maliva-avt-0068/7327283645707042821~tplv-tiktokx-cropcenter:1080:1080.jpeg?dr=9640&refresh_token=1dd6dce0&x-expires=1753189200&x-signature=EYygzwRF6Me4xFvouZer%2F8qAcDo%3D&t=4d5b0474&ps=13740610&shp=a5d48078&shcp=81f88b70&idc=useast5\",\"avatarMedium\":\"https://p16-common-sign-va.tiktokcdn-us.com/tos-maliva-avt-0068/7327283645707042821~tplv-tiktokx-cropcenter:720:720.jpeg?dr=9640&refresh_token=487369fd&x-expires=1753189200&x-signature=Ud4IX2uLRhcO4gs%2BgBbbRfk1z4c%3D&t=4d5b0474&ps=13740610&shp=a5d48078&shcp=81f88b70&idc=useast5\",\"avatarThumb\":\"https://p16-common-sign-va.tiktokcdn-us.com/tos-maliva-avt-0068/7327283645707042821~tplv-tiktokx-cropcenter:100:100.jpeg?dr=9640&refresh_token=beebe3db&x-expires=1753189200&x-signature=gh3tK5arHnFFGgxFk9epO%2Fymn%2Bw%3D&t=4d5b0474&ps=13740610&shp=a5d48078&shcp=81f88b70&idc=useast5\",\"signature\":\"Creator of “No, Dummy” ©️\\nIf you “love that shirt” it’s here 👇\",\"createTime\":1504434037,\"verified\":true,\"secUid\":\"MS4wLjABAAAANIoAF4iSkA-nsJMk0GV_WjorMS1Yq-ci6xQYQkTXzj7j9sioIf88buXitSDD-xxn\",\"ftc\":false,\"relation\":0,\"openFavorite\":false,\"commentSetting\":0,\"commerceUserInfo\":{\"commerceUser\":false},\"duetSetting\":0,\"stitchSetting\":0,\"privateAccount\":false,\"secret\":false,\"isADVirtual\":false,\"roomId\":\"\",\"uniqueIdModifyTime\":0,\"ttSeller\":false,\"downloadSetting\":0,\"profileTab\":{\"showMusicTab\":false,\"showQuestionTab\":true,\"showPlayListTab\":true},\"followingVisibility\":2,\"recommendReason\":\"\",\"nowInvitationCardUrl\":\"\",\"nickNameModifyTime\":0,\"isEmbedBanned\":false,\"canExpPlaylist\":true,\"profileEmbedPermission\":1,\"language\":\"en\",\"eventList\":[],\"suggestAccountBind\":false,\"isOrganization\":0,\"UserStoryStatus\":0},\"stats\":{\"followerCount\":1300000,\"followingCount\":3117,\"heart\":41300000,\"heartCount\":41300000,\"videoCount\":1882,\"diggCount\":0,\"friendCount\":683},\"statsV2\":{\"followerCount\":\"1341382\",\"followingCount\":\"3117\",\"heart\":\"41284929\",\"heartCount\":\"41284929\",\"videoCount\":\"1882\",\"diggCount\":\"0\",\"friendCount\":\"683\"},\"itemList\":[]}"
}