{
  "timestamp": "2025-07-20T13:19:08.872Z",
  "platform": "TikTok",
  "apiType": "Profile",
  "handle": "barstoolohiostate",
  "requestUrl": "https://api.scrapecreators.com/v1/tiktok/profile?handle=barstoolohiostate",
  "responseStatus": 200,
  "responseTime": 1894,
  "rawResponse": "{\"user\":{\"id\":\"6744512442703807493\",\"shortId\":\"\",\"uniqueId\":\"barstoolohiostate\",\"nickname\":\"BarstoolOhioState\",\"avatarLarger\":\"https://p16-pu-sign-useast8.tiktokcdn-us.com/tos-useast5-avt-0068-tx/6f83156e09040f755bc7cbb8a668f326~tplv-tiktokx-cropcenter:1080:1080.jpeg?dr=9640&refresh_token=c2109667&x-expires=1753189200&x-signature=oL2C07d6zPB%2BGIm%2B1KC3T%2BaHP%2BM%3D&t=4d5b0474&ps=13740610&shp=a5d48078&shcp=81f88b70&idc=useast5\",\"avatarMedium\":\"https://p19-pu-sign-useast8.tiktokcdn-us.com/tos-useast5-avt-0068-tx/6f83156e09040f755bc7cbb8a668f326~tplv-tiktokx-cropcenter:720:720.jpeg?dr=9640&refresh_token=8fb38b9f&x-expires=1753189200&x-signature=DBWbsZ5Qa5Z0Enz3pM6vQJhWG5Y%3D&t=4d5b0474&ps=13740610&shp=a5d48078&shcp=81f88b70&idc=useast5\",\"avatarThumb\":\"https://p19-pu-sign-useast8.tiktokcdn-us.com/tos-useast5-avt-0068-tx/6f83156e09040f755bc7cbb8a668f326~tplv-tiktokx-cropcenter:100:100.jpeg?dr=9640&refresh_token=06a84069&x-expires=1753189200&x-signature=QCHiMFVIxZnG5ITbstAE7zLOI24%3D&t=4d5b0474&ps=13740610&shp=a5d48078&shcp=81f88b70&idc=useast5\",\"signature\":\"Direct affiliate of @barstoolsports\\nNot affiliated with Ohio State\",\"createTime\":1570300560,\"verified\":false,\"secUid\":\"MS4wLjABAAAA2J7G3TBxodBpQmcpbxjj-fi3ZRmZiVWS28FTYIGdBUsmGy032114fhrMdPxRxWvt\",\"ftc\":false,\"relation\":0,\"openFavorite\":false,\"bioLink\":{\"link\":\"https://store.barstoolsports.com/collections/barstool-u\",\"risk\":0},\"commentSetting\":0,\"commerceUserInfo\":{\"commerceUser\":true,\"category\":\"Media & Entertainment\",\"categoryButton\":false},\"duetSetting\":0,\"stitchSetting\":0,\"privateAccount\":false,\"secret\":false,\"isADVirtual\":false,\"roomId\":\"\",\"uniqueIdModifyTime\":0,\"ttSeller\":false,\"downloadSetting\":0,\"profileTab\":{\"showMusicTab\":false,\"showQuestionTab\":false,\"showPlayListTab\":false},\"followingVisibility\":1,\"recommendReason\":\"\",\"nowInvitationCardUrl\":\"\",\"nickNameModifyTime\":0,\"isEmbedBanned\":false,\"canExpPlaylist\":true,\"profileEmbedPermission\":1,\"language\":\"en\",\"eventList\":[],\"suggestAccountBind\":false,\"isOrganization\":0,\"UserStoryStatus\":0},\"stats\":{\"followerCount\":67300,\"followingCount\":145,\"heart\":14900,\"heartCount\":14900,\"videoCount\":0,\"diggCount\":0,\"friendCount\":109},\"statsV2\":{\"followerCount\":\"67325\",\"followingCount\":\"145\",\"heart\":\"14891\",\"heartCount\":\"14891\",\"videoCount\":\"0\",\"diggCount\":\"0\",\"friendCount\":\"109\"},\"itemList\":[]}"
}