{
  "timestamp": "2025-07-20T13:15:34.754Z",
  "platform": "TikTok",
  "apiType": "Profile",
  "handle": "sports23355",
  "requestUrl": "https://api.scrapecreators.com/v1/tiktok/profile?handle=sports23355",
  "responseStatus": 200,
  "responseTime": 2001,
  "rawResponse": "{\"user\":{\"id\":\"7342775766503736362\",\"shortId\":\"\",\"uniqueId\":\"sports23355\",\"nickname\":\"sports\",\"avatarLarger\":\"https://p19-pu-sign-useast8.tiktokcdn-us.com/tos-useast5-avt-0068-tx/c80034ab69083467b4cd6d63c5df62a9~tplv-tiktokx-cropcenter:1080:1080.jpeg?dr=9640&refresh_token=60c75270&x-expires=1753189200&x-signature=fPvNsmb9Rn6E2hiGGejFZRDIrec%3D&t=4d5b0474&ps=13740610&shp=a5d48078&shcp=81f88b70&idc=useast5\",\"avatarMedium\":\"https://p19-pu-sign-useast8.tiktokcdn-us.com/tos-useast5-avt-0068-tx/c80034ab69083467b4cd6d63c5df62a9~tplv-tiktokx-cropcenter:720:720.jpeg?dr=9640&refresh_token=a87bae41&x-expires=1753189200&x-signature=EMLSF9%2BQrBhxlNiarO57dZrK%2B6w%3D&t=4d5b0474&ps=13740610&shp=a5d48078&shcp=81f88b70&idc=useast5\",\"avatarThumb\":\"https://p16-pu-sign-useast8.tiktokcdn-us.com/tos-useast5-avt-0068-tx/c80034ab69083467b4cd6d63c5df62a9~tplv-tiktokx-cropcenter:100:100.jpeg?dr=9640&refresh_token=10138305&x-expires=1753189200&x-signature=Gv%2F4SkWIVcLkSGL6ABhNRGFFJac%3D&t=4d5b0474&ps=13740610&shp=a5d48078&shcp=81f88b70&idc=useast5\",\"signature\":\"Sports ⚽\",\"createTime\":1709623380,\"verified\":false,\"secUid\":\"MS4wLjABAAAABcd2fUMRQOldC2OmUfM6tKPH8O8nmC3zwDm3WJgPt4zQRyWLSwbyAB9fzEwG4ZnA\",\"ftc\":false,\"relation\":0,\"openFavorite\":false,\"commentSetting\":0,\"commerceUserInfo\":{\"commerceUser\":false},\"duetSetting\":0,\"stitchSetting\":0,\"privateAccount\":false,\"secret\":false,\"isADVirtual\":false,\"roomId\":\"\",\"uniqueIdModifyTime\":0,\"ttSeller\":false,\"downloadSetting\":0,\"profileTab\":{\"showMusicTab\":false,\"showQuestionTab\":false,\"showPlayListTab\":false},\"followingVisibility\":1,\"recommendReason\":\"\",\"nowInvitationCardUrl\":\"\",\"nickNameModifyTime\":1720185289,\"isEmbedBanned\":false,\"canExpPlaylist\":true,\"profileEmbedPermission\":1,\"language\":\"en\",\"eventList\":[],\"suggestAccountBind\":false,\"isOrganization\":0,\"UserStoryStatus\":0},\"stats\":{\"followerCount\":13000,\"followingCount\":0,\"heart\":74400,\"heartCount\":74400,\"videoCount\":61,\"diggCount\":0,\"friendCount\":0},\"statsV2\":{\"followerCount\":\"12950\",\"followingCount\":\"0\",\"heart\":\"74373\",\"heartCount\":\"74373\",\"videoCount\":\"61\",\"diggCount\":\"0\",\"friendCount\":\"0\"},\"itemList\":[]}"
}