{
  "timestamp": "2025-07-12T12:47:01.571Z",
  "platform": "TikTok",
  "apiType": "Profile",
  "handle": "easportsfc",
  "requestUrl": "https://api.scrapecreators.com/v1/tiktok/profile?handle=easportsfc",
  "responseStatus": 200,
  "responseTime": 1724,
  "rawResponse": "{\"user\":{\"id\":\"6675428945385571334\",\"shortId\":\"\",\"uniqueId\":\"easportsfc\",\"nickname\":\"EA SPORTS FC\",\"avatarLarger\":\"https://p19-common-sign-useast2a.tiktokcdn-us.com/tos-useast2a-avt-0068-euttp/b0d9c522e4dadd5789631be6208a0014~tplv-tiktokx-cropcenter:1080:1080.jpeg?dr=9640&refresh_token=85c875b6&x-expires=1752494400&x-signature=Pq4rQRjxcOx6bBTzYHFUfa0Qwys%3D&t=4d5b0474&ps=13740610&shp=a5d48078&shcp=81f88b70&idc=useast5\",\"avatarMedium\":\"https://p16-common-sign-useast2a.tiktokcdn-us.com/tos-useast2a-avt-0068-euttp/b0d9c522e4dadd5789631be6208a0014~tplv-tiktokx-cropcenter:720:720.jpeg?dr=9640&refresh_token=01583be4&x-expires=1752494400&x-signature=33%2FCqROwBBNJXGT6pziviiWFT0I%3D&t=4d5b0474&ps=13740610&shp=a5d48078&shcp=81f88b70&idc=useast5\",\"avatarThumb\":\"https://p16-common-sign-useast2a.tiktokcdn-us.com/tos-useast2a-avt-0068-euttp/b0d9c522e4dadd5789631be6208a0014~tplv-tiktokx-cropcenter:100:100.jpeg?dr=9640&refresh_token=13ac5207&x-expires=1752494400&x-signature=MsgNZGosDmC39vqlXvriyoDmmck%3D&t=4d5b0474&ps=13740610&shp=a5d48078&shcp=81f88b70&idc=useast5\",\"signature\":\"Rated (E) for Everyone. Includes In-Game Purchases (Includes Random Items).\",\"createTime\":1559823579,\"verified\":true,\"secUid\":\"MS4wLjABAAAAE0mw_i71IcosXIpZWDvhvFKF2_BmAzRorMc84u2aJlQbn54gL67kfUG5rpNOfpHl\",\"ftc\":false,\"relation\":0,\"openFavorite\":false,\"bioLink\":{\"link\":\"https://linktr.ee/easportsfc\",\"risk\":0},\"commentSetting\":0,\"commerceUserInfo\":{\"commerceUser\":true,\"downLoadLink\":{\"ios\":\"\",\"android\":\"\"},\"category\":\"Gaming\",\"categoryButton\":false},\"duetSetting\":0,\"stitchSetting\":0,\"privateAccount\":false,\"secret\":false,\"isADVirtual\":false,\"roomId\":\"\",\"uniqueIdModifyTime\":0,\"ttSeller\":false,\"region\":\"ES\",\"downloadSetting\":0,\"profileTab\":{\"showMusicTab\":false,\"showQuestionTab\":false,\"showPlayListTab\":false},\"followingVisibility\":1,\"recommendReason\":\"\",\"nowInvitationCardUrl\":\"\",\"nickNameModifyTime\":1688144496,\"isEmbedBanned\":false,\"canExpPlaylist\":true,\"profileEmbedPermission\":1,\"language\":\"en\",\"eventList\":[],\"suggestAccountBind\":false,\"isOrganization\":0,\"UserStoryStatus\":0},\"stats\":{\"followerCount\":6100000,\"followingCount\":33,\"heart\":45100000,\"heartCount\":45100000,\"videoCount\":336,\"diggCount\":0,\"friendCount\":20},\"statsV2\":{\"followerCount\":\"6109938\",\"followingCount\":\"33\",\"heart\":\"45057606\",\"heartCount\":\"45057606\",\"videoCount\":\"336\",\"diggCount\":\"0\",\"friendCount\":\"20\"},\"itemList\":[]}"
}