{
  "timestamp": "2025-07-12T12:47:18.336Z",
  "platform": "TikTok",
  "apiType": "Profile",
  "handle": "pathfindersurvival",
  "requestUrl": "https://api.scrapecreators.com/v1/tiktok/profile?handle=pathfindersurvival",
  "responseStatus": 200,
  "responseTime": 1731,
  "rawResponse": "{\"user\":{\"id\":\"6908052035083404294\",\"shortId\":\"\",\"uniqueId\":\"pathfindersurvival\",\"nickname\":\"Dave Canterbury\",\"avatarLarger\":\"https://p16-common-sign-va.tiktokcdn-us.com/tos-maliva-avt-0068/0993ecb436471d1f607b1104ad98c81d~tplv-tiktokx-cropcenter:1080:1080.jpeg?dr=9640&refresh_token=cd2326cc&x-expires=1752494400&x-signature=mIypaGyzNcEKsZ%2Buh4oDB3InvQQ%3D&t=4d5b0474&ps=13740610&shp=a5d48078&shcp=81f88b70&idc=useast5\",\"avatarMedium\":\"https://p16-common-sign-va.tiktokcdn-us.com/tos-maliva-avt-0068/0993ecb436471d1f607b1104ad98c81d~tplv-tiktokx-cropcenter:720:720.jpeg?dr=9640&refresh_token=e011608b&x-expires=1752494400&x-signature=jzlHv6cWkzajYHjP2WFS1GePKzw%3D&t=4d5b0474&ps=13740610&shp=a5d48078&shcp=81f88b70&idc=useast5\",\"avatarThumb\":\"https://p16-common-sign-va.tiktokcdn-us.com/tos-maliva-avt-0068/0993ecb436471d1f607b1104ad98c81d~tplv-tiktokx-cropcenter:100:100.jpeg?dr=9640&refresh_token=be0d3646&x-expires=1752494400&x-signature=uj6Wv%2FNpRaYqBh1JQdgC0xBxp78%3D&t=4d5b0474&ps=13740610&shp=a5d48078&shcp=81f88b70&idc=useast5\",\"signature\":\"Owner of The Pathfinder School LLC, NY Times Best Selling Author \\\"BUSHCRAFT 101\\\"\",\"createTime\":1608406334,\"verified\":false,\"secUid\":\"MS4wLjABAAAA1CA2mqc9xPp6BohUp2ra22N2380fEqDCkvkGBSHmzYtGWrI21vugwFVM2nEYGusH\",\"ftc\":false,\"relation\":0,\"openFavorite\":false,\"bioLink\":{\"link\":\"Http://www.selfrelianceoutfitters.com\",\"risk\":3},\"commentSetting\":0,\"commerceUserInfo\":{\"commerceUser\":true,\"category\":\"Education & Training\",\"categoryButton\":false},\"duetSetting\":3,\"stitchSetting\":3,\"privateAccount\":false,\"secret\":false,\"isADVirtual\":false,\"roomId\":\"\",\"uniqueIdModifyTime\":0,\"ttSeller\":false,\"region\":\"US\",\"downloadSetting\":0,\"profileTab\":{\"showMusicTab\":false,\"showQuestionTab\":true,\"showPlayListTab\":false},\"followingVisibility\":1,\"recommendReason\":\"\",\"nowInvitationCardUrl\":\"\",\"nickNameModifyTime\":0,\"isEmbedBanned\":false,\"canExpPlaylist\":true,\"profileEmbedPermission\":1,\"language\":\"en\",\"eventList\":[],\"suggestAccountBind\":false,\"isOrganization\":0,\"UserStoryStatus\":0},\"stats\":{\"followerCount\":734900,\"followingCount\":48,\"heart\":4700000,\"heartCount\":4700000,\"videoCount\":414,\"diggCount\":0,\"friendCount\":29},\"statsV2\":{\"followerCount\":\"734904\",\"followingCount\":\"48\",\"heart\":\"4728430\",\"heartCount\":\"4728430\",\"videoCount\":\"414\",\"diggCount\":\"0\",\"friendCount\":\"29\"},\"itemList\":[]}"
}