{
  "timestamp": "2025-07-20T13:15:34.436Z",
  "platform": "TikTok",
  "apiType": "Profile",
  "handle": "easportsfc",
  "requestUrl": "https://api.scrapecreators.com/v1/tiktok/profile?handle=easportsfc",
  "responseStatus": 200,
  "responseTime": 1673,
  "rawResponse": "{\"user\":{\"id\":\"6675428945385571334\",\"shortId\":\"\",\"uniqueId\":\"easportsfc\",\"nickname\":\"EA SPORTS FC\",\"avatarLarger\":\"https://p19-common-sign-va.tiktokcdn-us.com/tos-maliva-avt-0068/58c52f6017be67b730ff8362628afea0~tplv-tiktokx-cropcenter:1080:1080.jpeg?dr=9640&refresh_token=283bfe2d&x-expires=1753189200&x-signature=Gx73r5csETq%2Bdtvx5Cwc0Tc%2Bcms%3D&t=4d5b0474&ps=13740610&shp=a5d48078&shcp=81f88b70&idc=useast8\",\"avatarMedium\":\"https://p16-common-sign-va.tiktokcdn-us.com/tos-maliva-avt-0068/58c52f6017be67b730ff8362628afea0~tplv-tiktokx-cropcenter:720:720.jpeg?dr=9640&refresh_token=b09c6726&x-expires=1753189200&x-signature=e1otf%2BkgAYhCKfTINYp85DqbMmk%3D&t=4d5b0474&ps=13740610&shp=a5d48078&shcp=81f88b70&idc=useast8\",\"avatarThumb\":\"https://p16-common-sign-va.tiktokcdn-us.com/tos-maliva-avt-0068/58c52f6017be67b730ff8362628afea0~tplv-tiktokx-cropcenter:100:100.jpeg?dr=9640&refresh_token=4916c2a1&x-expires=1753189200&x-signature=YT3DZcbWf7v3aojRI8ZU78DyO94%3D&t=4d5b0474&ps=13740610&shp=a5d48078&shcp=81f88b70&idc=useast8\",\"signature\":\"Rated (E) for Everyone. Includes In-Game Purchases (Includes Random Items).\",\"createTime\":1559823579,\"verified\":true,\"secUid\":\"MS4wLjABAAAAE0mw_i71IcosXIpZWDvhvFKF2_BmAzRorMc84u2aJlQbn54gL67kfUG5rpNOfpHl\",\"ftc\":false,\"relation\":0,\"openFavorite\":false,\"bioLink\":{\"link\":\"https://linktr.ee/easportsfc\",\"risk\":0},\"commentSetting\":0,\"commerceUserInfo\":{\"commerceUser\":true,\"downLoadLink\":{\"android\":\"\",\"ios\":\"\"},\"category\":\"Gaming\",\"categoryButton\":false},\"duetSetting\":0,\"stitchSetting\":0,\"privateAccount\":false,\"secret\":false,\"isADVirtual\":false,\"roomId\":\"\",\"uniqueIdModifyTime\":0,\"ttSeller\":false,\"downloadSetting\":0,\"profileTab\":{\"showMusicTab\":false,\"showQuestionTab\":false,\"showPlayListTab\":false},\"followingVisibility\":1,\"recommendReason\":\"\",\"nowInvitationCardUrl\":\"\",\"nickNameModifyTime\":1688144496,\"isEmbedBanned\":false,\"canExpPlaylist\":true,\"profileEmbedPermission\":1,\"language\":\"en\",\"eventList\":[],\"suggestAccountBind\":false,\"isOrganization\":0,\"UserStoryStatus\":0},\"stats\":{\"followerCount\":6300000,\"followingCount\":38,\"heart\":47400000,\"heartCount\":47400000,\"videoCount\":342,\"diggCount\":0,\"friendCount\":23},\"statsV2\":{\"followerCount\":\"6325868\",\"followingCount\":\"38\",\"heart\":\"47415152\",\"heartCount\":\"47415152\",\"videoCount\":\"342\",\"diggCount\":\"0\",\"friendCount\":\"23\"},\"itemList\":[]}"
}