{
  "timestamp": "2025-07-20T13:15:24.701Z",
  "platform": "TikTok",
  "apiType": "Profile",
  "handle": "barstoolisu",
  "requestUrl": "https://api.scrapecreators.com/v1/tiktok/profile?handle=barstoolisu",
  "responseStatus": 200,
  "responseTime": 1543,
  "rawResponse": "{\"user\":{\"id\":\"6793100468581598213\",\"shortId\":\"\",\"uniqueId\":\"barstoolisu\",\"nickname\":\"barstoolisu\",\"avatarLarger\":\"https://p16-common-sign-va.tiktokcdn-us.com/tos-maliva-avt-0068/7321373606146965510~tplv-tiktokx-cropcenter:1080:1080.jpeg?dr=9640&refresh_token=bcebf322&x-expires=1753189200&x-signature=KbUMB5znaQvpBKMuLIQM87Az3kY%3D&t=4d5b0474&ps=13740610&shp=a5d48078&shcp=81f88b70&idc=useast5\",\"avatarMedium\":\"https://p19-common-sign-va.tiktokcdn-us.com/tos-maliva-avt-0068/7321373606146965510~tplv-tiktokx-cropcenter:720:720.jpeg?dr=9640&refresh_token=afd86d1b&x-expires=1753189200&x-signature=a3MPitADXxqlxOK8uoecNDvLtQU%3D&t=4d5b0474&ps=13740610&shp=a5d48078&shcp=81f88b70&idc=useast5\",\"avatarThumb\":\"https://p16-common-sign-va.tiktokcdn-us.com/tos-maliva-avt-0068/7321373606146965510~tplv-tiktokx-cropcenter:100:100.jpeg?dr=9640&refresh_token=cb46747b&x-expires=1753189200&x-signature=F7%2FHHzl5ShQhW1nVNBh9qF1wOIk%3D&t=4d5b0474&ps=13740610&shp=a5d48078&shcp=81f88b70&idc=useast5\",\"signature\":\"Direct affiliate of @barstoolsports\\n\\nNot affiliated with ISU\\nFollow us on Insta\",\"createTime\":1581651722,\"verified\":false,\"secUid\":\"MS4wLjABAAAAIcvf5wAs88SA4uAsaEe88Spw3iH1r-9kkk7T8lIWzeAxJ86uRc8ut66NW5LLfw9g\",\"ftc\":false,\"relation\":0,\"openFavorite\":false,\"commentSetting\":0,\"commerceUserInfo\":{\"commerceUser\":true,\"category\":\"Media & Entertainment\",\"categoryButton\":false},\"duetSetting\":0,\"stitchSetting\":0,\"privateAccount\":false,\"secret\":false,\"isADVirtual\":false,\"roomId\":\"\",\"uniqueIdModifyTime\":0,\"ttSeller\":false,\"downloadSetting\":0,\"profileTab\":{\"showMusicTab\":false,\"showQuestionTab\":true,\"showPlayListTab\":false},\"followingVisibility\":1,\"recommendReason\":\"\",\"nowInvitationCardUrl\":\"\",\"nickNameModifyTime\":0,\"isEmbedBanned\":false,\"canExpPlaylist\":true,\"profileEmbedPermission\":1,\"language\":\"en\",\"eventList\":[],\"suggestAccountBind\":false,\"isOrganization\":0,\"UserStoryStatus\":0},\"stats\":{\"followerCount\":22100,\"followingCount\":115,\"heart\":21500,\"heartCount\":21500,\"videoCount\":0,\"diggCount\":0,\"friendCount\":84},\"statsV2\":{\"followerCount\":\"22081\",\"followingCount\":\"115\",\"heart\":\"21528\",\"heartCount\":\"21528\",\"videoCount\":\"0\",\"diggCount\":\"0\",\"friendCount\":\"84\"},\"itemList\":[]}"
}